{"traceEvents":[{"pid":714025,"tid":714025,"ph":"X","ts":1880,"dur":665,"name":"Source","args":{"detail":"/usr/include/features.h"}},{"pid":714025,"tid":714025,"ph":"X","ts":1638,"dur":1292,"name":"Source","args":{"detail":"/home/kris/Projects/clang-p2996/build/bin/../include/c++/v1/__config"}},{"pid":714025,"tid":714025,"ph":"X","ts":3752,"dur":537,"name":"Source","args":{"detail":"/home/kris/Projects/clang-p2996/build/bin/../include/c++/v1/__type_traits/integral_constant.h"}},{"pid":714025,"tid":714025,"ph":"X","ts":3738,"dur":893,"name":"Source","args":{"detail":"/home/kris/Projects/clang-p2996/build/bin/../include/c++/v1/__type_traits/is_referenceable.h"}},{"pid":714025,"tid":714025,"ph":"X","ts":3723,"dur":1015,"name":"Source","args":{"detail":"/home/kris/Projects/clang-p2996/build/bin/../include/c++/v1/__type_traits/add_lvalue_reference.h"}},{"pid":714025,"tid":714025,"ph":"X","ts":5236,"dur":3056,"name":"Source","args":{"detail":"/home/kris/Projects/clang-p2996/build/bin/../include/c++/v1/cstddef"}},{"pid":714025,"tid":714025,"ph":"X","ts":5213,"dur":3283,"name":"Source","args":{"detail":"/home/kris/Projects/clang-p2996/build/bin/../include/c++/v1/__type_traits/remove_reference.h"}},{"pid":714025,"tid":714025,"ph":"X","ts":4768,"dur":3828,"name":"Source","args":{"detail":"/home/kris/Projects/clang-p2996/build/bin/../include/c++/v1/__type_traits/add_pointer.h"}},{"pid":714025,"tid":714025,"ph":"X","ts":8857,"dur":2203,"name":"Source","args":{"detail":"/home/kris/Projects/clang-p2996/build/bin/../include/c++/v1/__type_traits/aligned_storage.h"}},{"pid":714025,"tid":714025,"ph":"X","ts":11633,"dur":552,"name":"Source","args":{"detail":"/home/kris/Projects/clang-p2996/build/bin/../include/c++/v1/__type_traits/apply_cv.h"}},{"pid":714025,"tid":714025,"ph":"X","ts":12230,"dur":619,"name":"Source","args":{"detail":"/home/kris/Projects/clang-p2996/build/bin/../include/c++/v1/__fwd/pair.h"}},{"pid":714025,"tid":714025,"ph":"X","ts":12211,"dur":1088,"name":"Source","args":{"detail":"/home/kris/Projects/clang-p2996/build/bin/../include/c++/v1/__type_traits/can_extract_key.h"}},{"pid":714025,"tid":714025,"ph":"X","ts":13387,"dur":903,"name":"Source","args":{"detail":"/home/kris/Projects/clang-p2996/build/bin/../include/c++/v1/__type_traits/decay.h"}},{"pid":714025,"tid":714025,"ph":"X","ts":13368,"dur":1906,"name":"Source","args":{"detail":"/home/kris/Projects/clang-p2996/build/bin/../include/c++/v1/__type_traits/common_type.h"}},{"pid":714025,"tid":714025,"ph":"X","ts":13346,"dur":3540,"name":"Source","args":{"detail":"/home/kris/Projects/clang-p2996/build/bin/../include/c++/v1/__type_traits/common_reference.h"}},{"pid":714025,"tid":714025,"ph":"X","ts":18417,"dur":3308,"name":"Source","args":{"detail":"/home/kris/Projects/clang-p2996/build/bin/../include/c++/v1/__type_traits/invoke.h"}},{"pid":714025,"tid":714025,"ph":"X","ts":28351,"dur":911,"name":"Source","args":{"detail":"/home/kris/Projects/clang-p2996/build/bin/../include/c++/v1/__type_traits/is_swappable.h"}},{"pid":714025,"tid":714025,"ph":"X","ts":29959,"dur":682,"name":"Source","args":{"detail":"/usr/include/stdint.h"}},{"pid":714025,"tid":714025,"ph":"X","ts":29924,"dur":825,"name":"Source","args":{"detail":"/home/kris/Projects/clang-p2996/build/lib/clang/19/include/stdint.h"}},{"pid":714025,"tid":714025,"ph":"X","ts":29881,"dur":869,"name":"Source","args":{"detail":"/home/kris/Projects/clang-p2996/build/bin/../include/c++/v1/stdint.h"}},{"pid":714025,"tid":714025,"ph":"X","ts":29861,"dur":1098,"name":"Source","args":{"detail":"/home/kris/Projects/clang-p2996/build/bin/../include/c++/v1/cstdint"}},{"pid":714025,"tid":714025,"ph":"X","ts":29838,"dur":1289,"name":"Source","args":{"detail":"/home/kris/Projects/clang-p2996/build/bin/../include/c++/v1/__type_traits/is_trivially_copyable.h"}},{"pid":714025,"tid":714025,"ph":"X","ts":1608,"dur":32460,"name":"Source","args":{"detail":"/home/kris/Projects/clang-p2996/build/bin/../include/c++/v1/type_traits"}},{"pid":714025,"tid":714025,"ph":"X","ts":1572,"dur":32639,"name":"Source","args":{"detail":"/usr/include/boost/mp11/integral.hpp"}},{"pid":714025,"tid":714025,"ph":"X","ts":34422,"dur":1709,"name":"Source","args":{"detail":"/usr/include/boost/mp11/utility.hpp"}},{"pid":714025,"tid":714025,"ph":"X","ts":34402,"dur":3153,"name":"Source","args":{"detail":"/usr/include/boost/mp11/detail/mp_append.hpp"}},{"pid":714025,"tid":714025,"ph":"X","ts":1558,"dur":37009,"name":"Source","args":{"detail":"/usr/include/boost/mp11/list.hpp"}},{"pid":714025,"tid":714025,"ph":"X","ts":38668,"dur":1535,"name":"Source","args":{"detail":"/usr/include/boost/mp11/function.hpp"}},{"pid":714025,"tid":714025,"ph":"X","ts":38649,"dur":2945,"name":"Source","args":{"detail":"/usr/include/boost/mp11/set.hpp"}},{"pid":714025,"tid":714025,"ph":"X","ts":41915,"dur":610,"name":"Source","args":{"detail":"/home/kris/Projects/clang-p2996/build/bin/../include/c++/v1/__utility/as_const.h"}},{"pid":714025,"tid":714025,"ph":"X","ts":43545,"dur":549,"name":"ParseClass","args":{"detail":"std::__libcpp_numeric_limits"}},{"pid":714025,"tid":714025,"ph":"X","ts":44206,"dur":616,"name":"ParseClass","args":{"detail":"std::__libcpp_numeric_limits"}},{"pid":714025,"tid":714025,"ph":"X","ts":44837,"dur":584,"name":"ParseClass","args":{"detail":"std::__libcpp_numeric_limits"}},{"pid":714025,"tid":714025,"ph":"X","ts":45438,"dur":676,"name":"ParseClass","args":{"detail":"std::__libcpp_numeric_limits"}},{"pid":714025,"tid":714025,"ph":"X","ts":46135,"dur":673,"name":"ParseClass","args":{"detail":"std::__libcpp_numeric_limits"}},{"pid":714025,"tid":714025,"ph":"X","ts":46828,"dur":764,"name":"ParseClass","args":{"detail":"std::__libcpp_numeric_limits"}},{"pid":714025,"tid":714025,"ph":"X","ts":47610,"dur":535,"name":"ParseClass","args":{"detail":"std::numeric_limits"}},{"pid":714025,"tid":714025,"ph":"X","ts":43370,"dur":5150,"name":"Source","args":{"detail":"/home/kris/Projects/clang-p2996/build/bin/../include/c++/v1/limits"}},{"pid":714025,"tid":714025,"ph":"X","ts":42813,"dur":6786,"name":"Source","args":{"detail":"/home/kris/Projects/clang-p2996/build/bin/../include/c++/v1/__utility/cmp.h"}},{"pid":714025,"tid":714025,"ph":"X","ts":49649,"dur":1549,"name":"Source","args":{"detail":"/home/kris/Projects/clang-p2996/build/bin/../include/c++/v1/__utility/exception_guard.h"}},{"pid":714025,"tid":714025,"ph":"X","ts":51638,"dur":509,"name":"Source","args":{"detail":"/home/kris/Projects/clang-p2996/build/bin/../include/c++/v1/__utility/in_place.h"}},{"pid":714025,"tid":714025,"ph":"X","ts":52187,"dur":526,"name":"Source","args":{"detail":"/home/kris/Projects/clang-p2996/build/bin/../include/c++/v1/__utility/integer_sequence.h"}},{"pid":714025,"tid":714025,"ph":"X","ts":53210,"dur":1802,"name":"ParseClass","args":{"detail":"std::partial_ordering"}},{"pid":714025,"tid":714025,"ph":"X","ts":53204,"dur":1817,"name":"ParseDeclarationOrFunctionDefinition","args":{"detail":"/home/kris/Projects/clang-p2996/build/bin/../include/c++/v1/__compare/ordering.h:43:1"}},{"pid":714025,"tid":714025,"ph":"X","ts":55196,"dur":1629,"name":"ParseClass","args":{"detail":"std::weak_ordering"}},{"pid":714025,"tid":714025,"ph":"X","ts":55189,"dur":1643,"name":"ParseDeclarationOrFunctionDefinition","args":{"detail":"/home/kris/Projects/clang-p2996/build/bin/../include/c++/v1/__compare/ordering.h:119:1"}},{"pid":714025,"tid":714025,"ph":"X","ts":56972,"dur":1903,"name":"ParseClass","args":{"detail":"std::strong_ordering"}},{"pid":714025,"tid":714025,"ph":"X","ts":56964,"dur":1917,"name":"ParseDeclarationOrFunctionDefinition","args":{"detail":"/home/kris/Projects/clang-p2996/build/bin/../include/c++/v1/__compare/ordering.h:189:1"}},{"pid":714025,"tid":714025,"ph":"X","ts":52824,"dur":6265,"name":"Source","args":{"detail":"/home/kris/Projects/clang-p2996/build/bin/../include/c++/v1/__compare/ordering.h"}},{"pid":714025,"tid":714025,"ph":"X","ts":52795,"dur":7487,"name":"Source","args":{"detail":"/home/kris/Projects/clang-p2996/build/bin/../include/c++/v1/__compare/common_comparison_category.h"}},{"pid":714025,"tid":714025,"ph":"X","ts":60352,"dur":1256,"name":"Source","args":{"detail":"/home/kris/Projects/clang-p2996/build/bin/../include/c++/v1/__compare/three_way_comparable.h"}},{"pid":714025,"tid":714025,"ph":"X","ts":60328,"dur":1522,"name":"Source","args":{"detail":"/home/kris/Projects/clang-p2996/build/bin/../include/c++/v1/__compare/synth_three_way.h"}},{"pid":714025,"tid":714025,"ph":"X","ts":62892,"dur":1486,"name":"Source","args":{"detail":"/home/kris/Projects/clang-p2996/build/bin/../include/c++/v1/__concepts/swappable.h"}},{"pid":714025,"tid":714025,"ph":"X","ts":62871,"dur":1632,"name":"Source","args":{"detail":"/home/kris/Projects/clang-p2996/build/bin/../include/c++/v1/__concepts/movable.h"}},{"pid":714025,"tid":714025,"ph":"X","ts":62422,"dur":2169,"name":"Source","args":{"detail":"/home/kris/Projects/clang-p2996/build/bin/../include/c++/v1/__concepts/copyable.h"}},{"pid":714025,"tid":714025,"ph":"X","ts":65298,"dur":659,"name":"Source","args":{"detail":"/home/kris/Projects/clang-p2996/build/bin/../include/c++/v1/__iterator/incrementable_traits.h"}},{"pid":714025,"tid":714025,"ph":"X","ts":66029,"dur":2524,"name":"Source","args":{"detail":"/home/kris/Projects/clang-p2996/build/bin/../include/c++/v1/__iterator/iterator_traits.h"}},{"pid":714025,"tid":714025,"ph":"X","ts":65994,"dur":3281,"name":"Source","args":{"detail":"/home/kris/Projects/clang-p2996/build/bin/../include/c++/v1/__iterator/iter_move.h"}},{"pid":714025,"tid":714025,"ph":"X","ts":69347,"dur":2120,"name":"Source","args":{"detail":"/home/kris/Projects/clang-p2996/build/bin/../include/c++/v1/__memory/pointer_traits.h"}},{"pid":714025,"tid":714025,"ph":"X","ts":64645,"dur":9595,"name":"Source","args":{"detail":"/home/kris/Projects/clang-p2996/build/bin/../include/c++/v1/__iterator/concepts.h"}},{"pid":714025,"tid":714025,"ph":"X","ts":62407,"dur":12297,"name":"Source","args":{"detail":"/home/kris/Projects/clang-p2996/build/bin/../include/c++/v1/__fwd/subrange.h"}},{"pid":714025,"tid":714025,"ph":"X","ts":74778,"dur":554,"name":"Source","args":{"detail":"/home/kris/Projects/clang-p2996/build/bin/../include/c++/v1/__tuple/tuple_like.h"}},{"pid":714025,"tid":714025,"ph":"X","ts":74756,"dur":1143,"name":"Source","args":{"detail":"/home/kris/Projects/clang-p2996/build/bin/../include/c++/v1/__tuple/pair_like.h"}},{"pid":714025,"tid":714025,"ph":"X","ts":75973,"dur":575,"name":"Source","args":{"detail":"/home/kris/Projects/clang-p2996/build/bin/../include/c++/v1/__tuple/tuple_element.h"}},{"pid":714025,"tid":714025,"ph":"X","ts":75955,"dur":1071,"name":"Source","args":{"detail":"/home/kris/Projects/clang-p2996/build/bin/../include/c++/v1/__tuple/make_tuple_types.h"}},{"pid":714025,"tid":714025,"ph":"X","ts":75933,"dur":2485,"name":"Source","args":{"detail":"/home/kris/Projects/clang-p2996/build/bin/../include/c++/v1/__tuple/sfinae_helpers.h"}},{"pid":714025,"tid":714025,"ph":"X","ts":79089,"dur":2820,"name":"ParseClass","args":{"detail":"std::pair"}},{"pid":714025,"tid":714025,"ph":"X","ts":52766,"dur":31665,"name":"Source","args":{"detail":"/home/kris/Projects/clang-p2996/build/bin/../include/c++/v1/__utility/pair.h"}},{"pid":714025,"tid":714025,"ph":"X","ts":86108,"dur":648,"name":"Source","args":{"detail":"/home/kris/Projects/clang-p2996/build/bin/../include/c++/v1/__type_traits/promote.h"}},{"pid":714025,"tid":714025,"ph":"X","ts":86085,"dur":2520,"name":"Source","args":{"detail":"/home/kris/Projects/clang-p2996/build/bin/../include/c++/v1/__math/exponential_functions.h"}},{"pid":714025,"tid":714025,"ph":"X","ts":88652,"dur":1661,"name":"Source","args":{"detail":"/home/kris/Projects/clang-p2996/build/bin/../include/c++/v1/__math/traits.h"}},{"pid":714025,"tid":714025,"ph":"X","ts":90504,"dur":2690,"name":"ParseClass","args":{"detail":"std::__strong_order::__fn"}},{"pid":714025,"tid":714025,"ph":"X","ts":90497,"dur":2701,"name":"ParseDeclarationOrFunctionDefinition","args":{"detail":"/home/kris/Projects/clang-p2996/build/bin/../include/c++/v1/__compare/strong_order.h:42:1"}},{"pid":714025,"tid":714025,"ph":"X","ts":85869,"dur":7423,"name":"Source","args":{"detail":"/home/kris/Projects/clang-p2996/build/bin/../include/c++/v1/__compare/strong_order.h"}},{"pid":714025,"tid":714025,"ph":"X","ts":93465,"dur":1413,"name":"ParseClass","args":{"detail":"std::__weak_order::__fn"}},{"pid":714025,"tid":714025,"ph":"X","ts":93458,"dur":1425,"name":"ParseDeclarationOrFunctionDefinition","args":{"detail":"/home/kris/Projects/clang-p2996/build/bin/../include/c++/v1/__compare/weak_order.h:35:1"}},{"pid":714025,"tid":714025,"ph":"X","ts":85846,"dur":9116,"name":"Source","args":{"detail":"/home/kris/Projects/clang-p2996/build/bin/../include/c++/v1/__compare/weak_order.h"}},{"pid":714025,"tid":714025,"ph":"X","ts":95122,"dur":681,"name":"ParseClass","args":{"detail":"std::__partial_order::__fn"}},{"pid":714025,"tid":714025,"ph":"X","ts":95115,"dur":692,"name":"ParseDeclarationOrFunctionDefinition","args":{"detail":"/home/kris/Projects/clang-p2996/build/bin/../include/c++/v1/__compare/partial_order.h:33:1"}},{"pid":714025,"tid":714025,"ph":"X","ts":85528,"dur":10351,"name":"Source","args":{"detail":"/home/kris/Projects/clang-p2996/build/bin/../include/c++/v1/__compare/partial_order.h"}},{"pid":714025,"tid":714025,"ph":"X","ts":95997,"dur":623,"name":"ParseClass","args":{"detail":"std::__compare_partial_order_fallback::__fn"}},{"pid":714025,"tid":714025,"ph":"X","ts":95991,"dur":632,"name":"ParseDeclarationOrFunctionDefinition","args":{"detail":"/home/kris/Projects/clang-p2996/build/bin/../include/c++/v1/__compare/compare_partial_order_fallback.h:30:1"}},{"pid":714025,"tid":714025,"ph":"X","ts":85511,"dur":11188,"name":"Source","args":{"detail":"/home/kris/Projects/clang-p2996/build/bin/../include/c++/v1/__compare/compare_partial_order_fallback.h"}},{"pid":714025,"tid":714025,"ph":"X","ts":96876,"dur":584,"name":"ParseClass","args":{"detail":"std::__compare_strong_order_fallback::__fn"}},{"pid":714025,"tid":714025,"ph":"X","ts":96869,"dur":594,"name":"ParseDeclarationOrFunctionDefinition","args":{"detail":"/home/kris/Projects/clang-p2996/build/bin/../include/c++/v1/__compare/compare_strong_order_fallback.h:30:1"}},{"pid":714025,"tid":714025,"ph":"X","ts":96746,"dur":791,"name":"Source","args":{"detail":"/home/kris/Projects/clang-p2996/build/bin/../include/c++/v1/__compare/compare_strong_order_fallback.h"}},{"pid":714025,"tid":714025,"ph":"X","ts":98090,"dur":590,"name":"ParseClass","args":{"detail":"std::__compare_weak_order_fallback::__fn"}},{"pid":714025,"tid":714025,"ph":"X","ts":98084,"dur":599,"name":"ParseDeclarationOrFunctionDefinition","args":{"detail":"/home/kris/Projects/clang-p2996/build/bin/../include/c++/v1/__compare/compare_weak_order_fallback.h:30:1"}},{"pid":714025,"tid":714025,"ph":"X","ts":97984,"dur":776,"name":"Source","args":{"detail":"/home/kris/Projects/clang-p2996/build/bin/../include/c++/v1/__compare/compare_weak_order_fallback.h"}},{"pid":714025,"tid":714025,"ph":"X","ts":98802,"dur":1765,"name":"Source","args":{"detail":"/home/kris/Projects/clang-p2996/build/bin/../include/c++/v1/__compare/is_eq.h"}},{"pid":714025,"tid":714025,"ph":"X","ts":85489,"dur":15119,"name":"Source","args":{"detail":"/home/kris/Projects/clang-p2996/build/bin/../include/c++/v1/compare"}},{"pid":714025,"tid":714025,"ph":"X","ts":41893,"dur":59275,"name":"Source","args":{"detail":"/home/kris/Projects/clang-p2996/build/bin/../include/c++/v1/utility"}},{"pid":714025,"tid":714025,"ph":"X","ts":41860,"dur":64372,"name":"Source","args":{"detail":"/usr/include/boost/mp11/detail/mp_with_index.hpp"}},{"pid":714025,"tid":714025,"ph":"X","ts":38619,"dur":75265,"name":"Source","args":{"detail":"/usr/include/boost/mp11/algorithm.hpp"}},{"pid":714025,"tid":714025,"ph":"X","ts":113939,"dur":819,"name":"Source","args":{"detail":"/usr/include/boost/mp11/map.hpp"}},{"pid":714025,"tid":714025,"ph":"X","ts":114798,"dur":571,"name":"Source","args":{"detail":"/usr/include/boost/mp11/bind.hpp"}},{"pid":714025,"tid":714025,"ph":"X","ts":115482,"dur":1150,"name":"Source","args":{"detail":"/home/kris/Projects/clang-p2996/build/bin/../include/c++/v1/__memory/allocator_arg_t.h"}},{"pid":714025,"tid":714025,"ph":"X","ts":116680,"dur":579,"name":"Source","args":{"detail":"/home/kris/Projects/clang-p2996/build/bin/../include/c++/v1/__tuple/find_index.h"}},{"pid":714025,"tid":714025,"ph":"X","ts":117771,"dur":938,"name":"ParseClass","args":{"detail":"std::__tuple_leaf"}},{"pid":714025,"tid":714025,"ph":"X","ts":118755,"dur":724,"name":"ParseClass","args":{"detail":"std::__tuple_leaf"}},{"pid":714025,"tid":714025,"ph":"X","ts":119641,"dur":990,"name":"ParseClass","args":{"detail":"std::__tuple_impl"}},{"pid":714025,"tid":714025,"ph":"X","ts":120846,"dur":6349,"name":"ParseClass","args":{"detail":"std::tuple"}},{"pid":714025,"tid":714025,"ph":"X","ts":115449,"dur":17395,"name":"Source","args":{"detail":"/home/kris/Projects/clang-p2996/build/bin/../include/c++/v1/tuple"}},{"pid":714025,"tid":714025,"ph":"X","ts":115409,"dur":18443,"name":"Source","args":{"detail":"/usr/include/boost/mp11/tuple.hpp"}},{"pid":714025,"tid":714025,"ph":"X","ts":1516,"dur":132337,"name":"Source","args":{"detail":"/usr/include/boost/mp11.hpp"}},{"pid":714025,"tid":714025,"ph":"X","ts":1125,"dur":140420,"name":"Frontend"},{"pid":714025,"tid":714025,"ph":"X","ts":141995,"dur":1110,"name":"Backend"},{"pid":714025,"tid":714025,"ph":"X","ts":5,"dur":143227,"name":"ExecuteCompiler"},{"pid":714025,"tid":714026,"ph":"X","ts":0,"dur":143226,"name":"Total ExecuteCompiler","args":{"count":1,"avg ms":143}},{"pid":714025,"tid":714027,"ph":"X","ts":0,"dur":140483,"name":"Total Frontend","args":{"count":2,"avg ms":70}},{"pid":714025,"tid":714028,"ph":"X","ts":0,"dur":132337,"name":"Total Source","args":{"count":1,"avg ms":132}},{"pid":714025,"tid":714029,"ph":"X","ts":0,"dur":52898,"name":"Total ParseClass","args":{"count":727,"avg ms":0}},{"pid":714025,"tid":714030,"ph":"X","ts":0,"dur":20617,"name":"Total ParseDeclarationOrFunctionDefinition","args":{"count":120,"avg ms":0}},{"pid":714025,"tid":714031,"ph":"X","ts":0,"dur":10401,"name":"Total ParseFunctionDefinition","args":{"count":200,"avg ms":0}},{"pid":714025,"tid":714032,"ph":"X","ts":0,"dur":2244,"name":"Total InstantiateClass","args":{"count":84,"avg ms":0}},{"pid":714025,"tid":714033,"ph":"X","ts":0,"dur":1110,"name":"Total Backend","args":{"count":1,"avg ms":1}},{"pid":714025,"tid":714034,"ph":"X","ts":0,"dur":401,"name":"Total InstantiateFunction","args":{"count":2,"avg ms":0}},{"pid":714025,"tid":714035,"ph":"X","ts":0,"dur":397,"name":"Total EvaluateAsConstantExpr","args":{"count":713,"avg ms":0}},{"pid":714025,"tid":714036,"ph":"X","ts":0,"dur":264,"name":"Total isPotentialConstantExpr","args":{"count":106,"avg ms":0}},{"pid":714025,"tid":714037,"ph":"X","ts":0,"dur":249,"name":"Total EvaluateAsRValue","args":{"count":617,"avg ms":0}},{"pid":714025,"tid":714038,"ph":"X","ts":0,"dur":242,"name":"Total EvaluateAsInitializer","args":{"count":203,"avg ms":0}},{"pid":714025,"tid":714039,"ph":"X","ts":0,"dur":199,"name":"Total CodeGenPasses","args":{"count":1,"avg ms":0}},{"pid":714025,"tid":714040,"ph":"X","ts":0,"dur":183,"name":"Total OptModule","args":{"count":1,"avg ms":0}},{"pid":714025,"tid":714041,"ph":"X","ts":0,"dur":180,"name":"Total EvaluateAsBooleanCondition","args":{"count":114,"avg ms":0}},{"pid":714025,"tid":714042,"ph":"X","ts":0,"dur":118,"name":"Total EvaluateForOverflow","args":{"count":52,"avg ms":0}},{"pid":714025,"tid":714043,"ph":"X","ts":0,"dur":36,"name":"Total Optimizer","args":{"count":1,"avg ms":0}},{"pid":714025,"tid":714044,"ph":"X","ts":0,"dur":20,"name":"Total EvaluateAsInt","args":{"count":33,"avg ms":0}},{"pid":714025,"tid":714045,"ph":"X","ts":0,"dur":15,"name":"Total EvaluateKnownConstInt","args":{"count":141,"avg ms":0}},{"pid":714025,"tid":714046,"ph":"X","ts":0,"dur":12,"name":"Total isIntegerConstantExpr","args":{"count":17,"avg ms":0}},{"pid":714025,"tid":714047,"ph":"X","ts":0,"dur":11,"name":"Total AlwaysInlinerPass","args":{"count":1,"avg ms":0}},{"pid":714025,"tid":714048,"ph":"X","ts":0,"dur":9,"name":"Total CoroConditionalWrapper","args":{"count":1,"avg ms":0}},{"pid":714025,"tid":714049,"ph":"X","ts":0,"dur":1,"name":"Total ProfileSummaryAnalysis","args":{"count":1,"avg ms":0}},{"pid":714025,"tid":714050,"ph":"X","ts":0,"dur":1,"name":"Total ModuleToFunctionPassAdaptor","args":{"count":1,"avg ms":0}},{"pid":714025,"tid":714051,"ph":"X","ts":0,"dur":0,"name":"Total InnerAnalysisManagerProxy<AnalysisManager<Function>, Module>","args":{"count":1,"avg ms":0}},{"pid":714025,"tid":714052,"ph":"X","ts":0,"dur":0,"name":"Total PerformPendingInstantiations","args":{"count":1,"avg ms":0}},{"cat":"","pid":714025,"tid":714025,"ts":0,"ph":"M","name":"process_name","args":{"name":"clang++-19"}},{"cat":"","pid":714025,"tid":714025,"ts":0,"ph":"M","name":"thread_name","args":{"name":"clang++-19"}}],"beginningOfTime":1713595487438759}