{"traceEvents":[{"pid":712215,"tid":712215,"ph":"X","ts":3240,"dur":546,"name":"ParseClass","args":{"detail":"mp::vector"}},{"pid":712215,"tid":712215,"ph":"X","ts":1537,"dur":3078,"name":"Source","args":{"detail":"/usr/include/mp"}},{"pid":712215,"tid":712215,"ph":"X","ts":5180,"dur":4142,"name":"InstantiateFunction","args":{"detail":"drop_impl<0UL, x<0>, x<1>, x<2>, x<3>, x<4>, x<5>, x<6>, x<7>, x<8>, x<9>, x<10>, x<11>, x<12>, x<13>, x<14>, x<15>, x<16>, x<17>, x<18>, x<19>, x<20>, x<21>, x<22>, x<23>, x<24>, x<25>, x<26>, x<27>, x<28>, x<29>, x<30>, x<31>, x<32>, x<33>, x<34>, x<35>, x<36>, x<37>, x<38>, x<39>, x<40>, x<41>, x<42>, x<43>, x<44>, x<45>, x<46>, x<47>, x<48>, x<49>>"}},{"pid":712215,"tid":712215,"ph":"X","ts":10273,"dur":4379,"name":"InstantiateFunction","args":{"detail":"mp::apply()::(anonymous class)::operator()<0UL, 1UL, 2UL, 3UL, 4UL, 5UL, 6UL, 7UL, 8UL, 9UL, 10UL, 11UL, 12UL, 13UL, 14UL, 15UL, 16UL, 17UL, 18UL, 19UL, 20UL, 21UL, 22UL, 23UL, 24UL, 25UL, 26UL, 27UL, 28UL, 29UL, 30UL, 31UL, 32UL, 33UL, 34UL, 35UL, 36UL, 37UL, 38UL, 39UL, 40UL, 41UL, 42UL, 43UL, 44UL, 45UL, 46UL, 47UL, 48UL, 49UL>"}},{"pid":712215,"tid":712215,"ph":"X","ts":9757,"dur":5037,"name":"InstantiateFunction","args":{"detail":"mp::apply<type_list, mp::array<mp::meta_t, sizeof...(Ts) - 0UL>{{&info, &info, &info, &info, &info, &info, &info, &info, &info, &info, ...}}>"}},{"pid":712215,"tid":712215,"ph":"X","ts":15113,"dur":635,"name":"InstantiateFunction","args":{"detail":"drop_impl<1UL, x<0>, x<1>, x<2>, x<3>, x<4>, x<5>, x<6>, x<7>, x<8>, x<9>, x<10>, x<11>, x<12>, x<13>, x<14>, x<15>, x<16>, x<17>, x<18>, x<19>, x<20>, x<21>, x<22>, x<23>, x<24>, x<25>, x<26>, x<27>, x<28>, x<29>, x<30>, x<31>, x<32>, x<33>, x<34>, x<35>, x<36>, x<37>, x<38>, x<39>, x<40>, x<41>, x<42>, x<43>, x<44>, x<45>, x<46>, x<47>, x<48>, x<49>>"}},{"pid":712215,"tid":712215,"ph":"X","ts":16695,"dur":2048,"name":"InstantiateFunction","args":{"detail":"mp::apply()::(anonymous class)::operator()<0UL, 1UL, 2UL, 3UL, 4UL, 5UL, 6UL, 7UL, 8UL, 9UL, 10UL, 11UL, 12UL, 13UL, 14UL, 15UL, 16UL, 17UL, 18UL, 19UL, 20UL, 21UL, 22UL, 23UL, 24UL, 25UL, 26UL, 27UL, 28UL, 29UL, 30UL, 31UL, 32UL, 33UL, 34UL, 35UL, 36UL, 37UL, 38UL, 39UL, 40UL, 41UL, 42UL, 43UL, 44UL, 45UL, 46UL, 47UL, 48UL>"}},{"pid":712215,"tid":712215,"ph":"X","ts":16155,"dur":2728,"name":"InstantiateFunction","args":{"detail":"mp::apply<type_list, mp::array<mp::meta_t, sizeof...(Ts) - 1UL>{{&info, &info, &info, &info, &info, &info, &info, &info, &info, &info, ...}}>"}},{"pid":712215,"tid":712215,"ph":"X","ts":19202,"dur":741,"name":"InstantiateFunction","args":{"detail":"drop_impl<2UL, x<0>, x<1>, x<2>, x<3>, x<4>, x<5>, x<6>, x<7>, x<8>, x<9>, x<10>, x<11>, x<12>, x<13>, x<14>, x<15>, x<16>, x<17>, x<18>, x<19>, x<20>, x<21>, x<22>, x<23>, x<24>, x<25>, x<26>, x<27>, x<28>, x<29>, x<30>, x<31>, x<32>, x<33>, x<34>, x<35>, x<36>, x<37>, x<38>, x<39>, x<40>, x<41>, x<42>, x<43>, x<44>, x<45>, x<46>, x<47>, x<48>, x<49>>"}},{"pid":712215,"tid":712215,"ph":"X","ts":20906,"dur":2013,"name":"InstantiateFunction","args":{"detail":"mp::apply()::(anonymous class)::operator()<0UL, 1UL, 2UL, 3UL, 4UL, 5UL, 6UL, 7UL, 8UL, 9UL, 10UL, 11UL, 12UL, 13UL, 14UL, 15UL, 16UL, 17UL, 18UL, 19UL, 20UL, 21UL, 22UL, 23UL, 24UL, 25UL, 26UL, 27UL, 28UL, 29UL, 30UL, 31UL, 32UL, 33UL, 34UL, 35UL, 36UL, 37UL, 38UL, 39UL, 40UL, 41UL, 42UL, 43UL, 44UL, 45UL, 46UL, 47UL>"}},{"pid":712215,"tid":712215,"ph":"X","ts":20360,"dur":2697,"name":"InstantiateFunction","args":{"detail":"mp::apply<type_list, mp::array<mp::meta_t, sizeof...(Ts) - 2UL>{{&info, &info, &info, &info, &info, &info, &info, &info, &info, &info, ...}}>"}},{"pid":712215,"tid":712215,"ph":"X","ts":23388,"dur":616,"name":"InstantiateFunction","args":{"detail":"drop_impl<3UL, x<0>, x<1>, x<2>, x<3>, x<4>, x<5>, x<6>, x<7>, x<8>, x<9>, x<10>, x<11>, x<12>, x<13>, x<14>, x<15>, x<16>, x<17>, x<18>, x<19>, x<20>, x<21>, x<22>, x<23>, x<24>, x<25>, x<26>, x<27>, x<28>, x<29>, x<30>, x<31>, x<32>, x<33>, x<34>, x<35>, x<36>, x<37>, x<38>, x<39>, x<40>, x<41>, x<42>, x<43>, x<44>, x<45>, x<46>, x<47>, x<48>, x<49>>"}},{"pid":712215,"tid":712215,"ph":"X","ts":24910,"dur":2055,"name":"InstantiateFunction","args":{"detail":"mp::apply()::(anonymous class)::operator()<0UL, 1UL, 2UL, 3UL, 4UL, 5UL, 6UL, 7UL, 8UL, 9UL, 10UL, 11UL, 12UL, 13UL, 14UL, 15UL, 16UL, 17UL, 18UL, 19UL, 20UL, 21UL, 22UL, 23UL, 24UL, 25UL, 26UL, 27UL, 28UL, 29UL, 30UL, 31UL, 32UL, 33UL, 34UL, 35UL, 36UL, 37UL, 38UL, 39UL, 40UL, 41UL, 42UL, 43UL, 44UL, 45UL, 46UL>"}},{"pid":712215,"tid":712215,"ph":"X","ts":24392,"dur":2717,"name":"InstantiateFunction","args":{"detail":"mp::apply<type_list, mp::array<mp::meta_t, sizeof...(Ts) - 3UL>{{&info, &info, &info, &info, &info, &info, &info, &info, &info, &info, ...}}>"}},{"pid":712215,"tid":712215,"ph":"X","ts":27423,"dur":614,"name":"InstantiateFunction","args":{"detail":"drop_impl<4UL, x<0>, x<1>, x<2>, x<3>, x<4>, x<5>, x<6>, x<7>, x<8>, x<9>, x<10>, x<11>, x<12>, x<13>, x<14>, x<15>, x<16>, x<17>, x<18>, x<19>, x<20>, x<21>, x<22>, x<23>, x<24>, x<25>, x<26>, x<27>, x<28>, x<29>, x<30>, x<31>, x<32>, x<33>, x<34>, x<35>, x<36>, x<37>, x<38>, x<39>, x<40>, x<41>, x<42>, x<43>, x<44>, x<45>, x<46>, x<47>, x<48>, x<49>>"}},{"pid":712215,"tid":712215,"ph":"X","ts":28931,"dur":1940,"name":"InstantiateFunction","args":{"detail":"mp::apply()::(anonymous class)::operator()<0UL, 1UL, 2UL, 3UL, 4UL, 5UL, 6UL, 7UL, 8UL, 9UL, 10UL, 11UL, 12UL, 13UL, 14UL, 15UL, 16UL, 17UL, 18UL, 19UL, 20UL, 21UL, 22UL, 23UL, 24UL, 25UL, 26UL, 27UL, 28UL, 29UL, 30UL, 31UL, 32UL, 33UL, 34UL, 35UL, 36UL, 37UL, 38UL, 39UL, 40UL, 41UL, 42UL, 43UL, 44UL, 45UL>"}},{"pid":712215,"tid":712215,"ph":"X","ts":28424,"dur":2586,"name":"InstantiateFunction","args":{"detail":"mp::apply<type_list, mp::array<mp::meta_t, sizeof...(Ts) - 4UL>{{&info, &info, &info, &info, &info, &info, &info, &info, &info, &info, ...}}>"}},{"pid":712215,"tid":712215,"ph":"X","ts":31323,"dur":611,"name":"InstantiateFunction","args":{"detail":"drop_impl<5UL, x<0>, x<1>, x<2>, x<3>, x<4>, x<5>, x<6>, x<7>, x<8>, x<9>, x<10>, x<11>, x<12>, x<13>, x<14>, x<15>, x<16>, x<17>, x<18>, x<19>, x<20>, x<21>, x<22>, x<23>, x<24>, x<25>, x<26>, x<27>, x<28>, x<29>, x<30>, x<31>, x<32>, x<33>, x<34>, x<35>, x<36>, x<37>, x<38>, x<39>, x<40>, x<41>, x<42>, x<43>, x<44>, x<45>, x<46>, x<47>, x<48>, x<49>>"}},{"pid":712215,"tid":712215,"ph":"X","ts":32817,"dur":1919,"name":"InstantiateFunction","args":{"detail":"mp::apply()::(anonymous class)::operator()<0UL, 1UL, 2UL, 3UL, 4UL, 5UL, 6UL, 7UL, 8UL, 9UL, 10UL, 11UL, 12UL, 13UL, 14UL, 15UL, 16UL, 17UL, 18UL, 19UL, 20UL, 21UL, 22UL, 23UL, 24UL, 25UL, 26UL, 27UL, 28UL, 29UL, 30UL, 31UL, 32UL, 33UL, 34UL, 35UL, 36UL, 37UL, 38UL, 39UL, 40UL, 41UL, 42UL, 43UL, 44UL>"}},{"pid":712215,"tid":712215,"ph":"X","ts":32312,"dur":2560,"name":"InstantiateFunction","args":{"detail":"mp::apply<type_list, mp::array<mp::meta_t, sizeof...(Ts) - 5UL>{{&info, &info, &info, &info, &info, &info, &info, &info, &info, &info, ...}}>"}},{"pid":712215,"tid":712215,"ph":"X","ts":35199,"dur":645,"name":"InstantiateFunction","args":{"detail":"drop_impl<6UL, x<0>, x<1>, x<2>, x<3>, x<4>, x<5>, x<6>, x<7>, x<8>, x<9>, x<10>, x<11>, x<12>, x<13>, x<14>, x<15>, x<16>, x<17>, x<18>, x<19>, x<20>, x<21>, x<22>, x<23>, x<24>, x<25>, x<26>, x<27>, x<28>, x<29>, x<30>, x<31>, x<32>, x<33>, x<34>, x<35>, x<36>, x<37>, x<38>, x<39>, x<40>, x<41>, x<42>, x<43>, x<44>, x<45>, x<46>, x<47>, x<48>, x<49>>"}},{"pid":712215,"tid":712215,"ph":"X","ts":36721,"dur":1879,"name":"InstantiateFunction","args":{"detail":"mp::apply()::(anonymous class)::operator()<0UL, 1UL, 2UL, 3UL, 4UL, 5UL, 6UL, 7UL, 8UL, 9UL, 10UL, 11UL, 12UL, 13UL, 14UL, 15UL, 16UL, 17UL, 18UL, 19UL, 20UL, 21UL, 22UL, 23UL, 24UL, 25UL, 26UL, 27UL, 28UL, 29UL, 30UL, 31UL, 32UL, 33UL, 34UL, 35UL, 36UL, 37UL, 38UL, 39UL, 40UL, 41UL, 42UL, 43UL>"}},{"pid":712215,"tid":712215,"ph":"X","ts":36226,"dur":2527,"name":"InstantiateFunction","args":{"detail":"mp::apply<type_list, mp::array<mp::meta_t, sizeof...(Ts) - 6UL>{{&info, &info, &info, &info, &info, &info, &info, &info, &info, &info, ...}}>"}},{"pid":712215,"tid":712215,"ph":"X","ts":39073,"dur":628,"name":"InstantiateFunction","args":{"detail":"drop_impl<7UL, x<0>, x<1>, x<2>, x<3>, x<4>, x<5>, x<6>, x<7>, x<8>, x<9>, x<10>, x<11>, x<12>, x<13>, x<14>, x<15>, x<16>, x<17>, x<18>, x<19>, x<20>, x<21>, x<22>, x<23>, x<24>, x<25>, x<26>, x<27>, x<28>, x<29>, x<30>, x<31>, x<32>, x<33>, x<34>, x<35>, x<36>, x<37>, x<38>, x<39>, x<40>, x<41>, x<42>, x<43>, x<44>, x<45>, x<46>, x<47>, x<48>, x<49>>"}},{"pid":712215,"tid":712215,"ph":"X","ts":40570,"dur":1809,"name":"InstantiateFunction","args":{"detail":"mp::apply()::(anonymous class)::operator()<0UL, 1UL, 2UL, 3UL, 4UL, 5UL, 6UL, 7UL, 8UL, 9UL, 10UL, 11UL, 12UL, 13UL, 14UL, 15UL, 16UL, 17UL, 18UL, 19UL, 20UL, 21UL, 22UL, 23UL, 24UL, 25UL, 26UL, 27UL, 28UL, 29UL, 30UL, 31UL, 32UL, 33UL, 34UL, 35UL, 36UL, 37UL, 38UL, 39UL, 40UL, 41UL, 42UL>"}},{"pid":712215,"tid":712215,"ph":"X","ts":40079,"dur":2428,"name":"InstantiateFunction","args":{"detail":"mp::apply<type_list, mp::array<mp::meta_t, sizeof...(Ts) - 7UL>{{&info, &info, &info, &info, &info, &info, &info, &info, &info, &info, ...}}>"}},{"pid":712215,"tid":712215,"ph":"X","ts":42825,"dur":595,"name":"InstantiateFunction","args":{"detail":"drop_impl<8UL, x<0>, x<1>, x<2>, x<3>, x<4>, x<5>, x<6>, x<7>, x<8>, x<9>, x<10>, x<11>, x<12>, x<13>, x<14>, x<15>, x<16>, x<17>, x<18>, x<19>, x<20>, x<21>, x<22>, x<23>, x<24>, x<25>, x<26>, x<27>, x<28>, x<29>, x<30>, x<31>, x<32>, x<33>, x<34>, x<35>, x<36>, x<37>, x<38>, x<39>, x<40>, x<41>, x<42>, x<43>, x<44>, x<45>, x<46>, x<47>, x<48>, x<49>>"}},{"pid":712215,"tid":712215,"ph":"X","ts":44287,"dur":1788,"name":"InstantiateFunction","args":{"detail":"mp::apply()::(anonymous class)::operator()<0UL, 1UL, 2UL, 3UL, 4UL, 5UL, 6UL, 7UL, 8UL, 9UL, 10UL, 11UL, 12UL, 13UL, 14UL, 15UL, 16UL, 17UL, 18UL, 19UL, 20UL, 21UL, 22UL, 23UL, 24UL, 25UL, 26UL, 27UL, 28UL, 29UL, 30UL, 31UL, 32UL, 33UL, 34UL, 35UL, 36UL, 37UL, 38UL, 39UL, 40UL, 41UL>"}},{"pid":712215,"tid":712215,"ph":"X","ts":43787,"dur":2415,"name":"InstantiateFunction","args":{"detail":"mp::apply<type_list, mp::array<mp::meta_t, sizeof...(Ts) - 8UL>{{&info, &info, &info, &info, &info, &info, &info, &info, &info, &info, ...}}>"}},{"pid":712215,"tid":712215,"ph":"X","ts":46651,"dur":604,"name":"InstantiateFunction","args":{"detail":"drop_impl<9UL, x<0>, x<1>, x<2>, x<3>, x<4>, x<5>, x<6>, x<7>, x<8>, x<9>, x<10>, x<11>, x<12>, x<13>, x<14>, x<15>, x<16>, x<17>, x<18>, x<19>, x<20>, x<21>, x<22>, x<23>, x<24>, x<25>, x<26>, x<27>, x<28>, x<29>, x<30>, x<31>, x<32>, x<33>, x<34>, x<35>, x<36>, x<37>, x<38>, x<39>, x<40>, x<41>, x<42>, x<43>, x<44>, x<45>, x<46>, x<47>, x<48>, x<49>>"}},{"pid":712215,"tid":712215,"ph":"X","ts":48134,"dur":1733,"name":"InstantiateFunction","args":{"detail":"mp::apply()::(anonymous class)::operator()<0UL, 1UL, 2UL, 3UL, 4UL, 5UL, 6UL, 7UL, 8UL, 9UL, 10UL, 11UL, 12UL, 13UL, 14UL, 15UL, 16UL, 17UL, 18UL, 19UL, 20UL, 21UL, 22UL, 23UL, 24UL, 25UL, 26UL, 27UL, 28UL, 29UL, 30UL, 31UL, 32UL, 33UL, 34UL, 35UL, 36UL, 37UL, 38UL, 39UL, 40UL>"}},{"pid":712215,"tid":712215,"ph":"X","ts":47621,"dur":2367,"name":"InstantiateFunction","args":{"detail":"mp::apply<type_list, mp::array<mp::meta_t, sizeof...(Ts) - 9UL>{{&info, &info, &info, &info, &info, &info, &info, &info, &info, &info, ...}}>"}},{"pid":712215,"tid":712215,"ph":"X","ts":50341,"dur":608,"name":"InstantiateFunction","args":{"detail":"drop_impl<10UL, x<0>, x<1>, x<2>, x<3>, x<4>, x<5>, x<6>, x<7>, x<8>, x<9>, x<10>, x<11>, x<12>, x<13>, x<14>, x<15>, x<16>, x<17>, x<18>, x<19>, x<20>, x<21>, x<22>, x<23>, x<24>, x<25>, x<26>, x<27>, x<28>, x<29>, x<30>, x<31>, x<32>, x<33>, x<34>, x<35>, x<36>, x<37>, x<38>, x<39>, x<40>, x<41>, x<42>, x<43>, x<44>, x<45>, x<46>, x<47>, x<48>, x<49>>"}},{"pid":712215,"tid":712215,"ph":"X","ts":51775,"dur":1722,"name":"InstantiateFunction","args":{"detail":"mp::apply()::(anonymous class)::operator()<0UL, 1UL, 2UL, 3UL, 4UL, 5UL, 6UL, 7UL, 8UL, 9UL, 10UL, 11UL, 12UL, 13UL, 14UL, 15UL, 16UL, 17UL, 18UL, 19UL, 20UL, 21UL, 22UL, 23UL, 24UL, 25UL, 26UL, 27UL, 28UL, 29UL, 30UL, 31UL, 32UL, 33UL, 34UL, 35UL, 36UL, 37UL, 38UL, 39UL>"}},{"pid":712215,"tid":712215,"ph":"X","ts":51297,"dur":2318,"name":"InstantiateFunction","args":{"detail":"mp::apply<type_list, mp::array<mp::meta_t, sizeof...(Ts) - 10UL>{{&info, &info, &info, &info, &info, &info, &info, &info, &info, &info, ...}}>"}},{"pid":712215,"tid":712215,"ph":"X","ts":53927,"dur":611,"name":"InstantiateFunction","args":{"detail":"drop_impl<11UL, x<0>, x<1>, x<2>, x<3>, x<4>, x<5>, x<6>, x<7>, x<8>, x<9>, x<10>, x<11>, x<12>, x<13>, x<14>, x<15>, x<16>, x<17>, x<18>, x<19>, x<20>, x<21>, x<22>, x<23>, x<24>, x<25>, x<26>, x<27>, x<28>, x<29>, x<30>, x<31>, x<32>, x<33>, x<34>, x<35>, x<36>, x<37>, x<38>, x<39>, x<40>, x<41>, x<42>, x<43>, x<44>, x<45>, x<46>, x<47>, x<48>, x<49>>"}},{"pid":712215,"tid":712215,"ph":"X","ts":55355,"dur":1652,"name":"InstantiateFunction","args":{"detail":"mp::apply()::(anonymous class)::operator()<0UL, 1UL, 2UL, 3UL, 4UL, 5UL, 6UL, 7UL, 8UL, 9UL, 10UL, 11UL, 12UL, 13UL, 14UL, 15UL, 16UL, 17UL, 18UL, 19UL, 20UL, 21UL, 22UL, 23UL, 24UL, 25UL, 26UL, 27UL, 28UL, 29UL, 30UL, 31UL, 32UL, 33UL, 34UL, 35UL, 36UL, 37UL, 38UL>"}},{"pid":712215,"tid":712215,"ph":"X","ts":54889,"dur":2234,"name":"InstantiateFunction","args":{"detail":"mp::apply<type_list, mp::array<mp::meta_t, sizeof...(Ts) - 11UL>{{&info, &info, &info, &info, &info, &info, &info, &info, &info, &info, ...}}>"}},{"pid":712215,"tid":712215,"ph":"X","ts":57440,"dur":608,"name":"InstantiateFunction","args":{"detail":"drop_impl<12UL, x<0>, x<1>, x<2>, x<3>, x<4>, x<5>, x<6>, x<7>, x<8>, x<9>, x<10>, x<11>, x<12>, x<13>, x<14>, x<15>, x<16>, x<17>, x<18>, x<19>, x<20>, x<21>, x<22>, x<23>, x<24>, x<25>, x<26>, x<27>, x<28>, x<29>, x<30>, x<31>, x<32>, x<33>, x<34>, x<35>, x<36>, x<37>, x<38>, x<39>, x<40>, x<41>, x<42>, x<43>, x<44>, x<45>, x<46>, x<47>, x<48>, x<49>>"}},{"pid":712215,"tid":712215,"ph":"X","ts":58846,"dur":1621,"name":"InstantiateFunction","args":{"detail":"mp::apply()::(anonymous class)::operator()<0UL, 1UL, 2UL, 3UL, 4UL, 5UL, 6UL, 7UL, 8UL, 9UL, 10UL, 11UL, 12UL, 13UL, 14UL, 15UL, 16UL, 17UL, 18UL, 19UL, 20UL, 21UL, 22UL, 23UL, 24UL, 25UL, 26UL, 27UL, 28UL, 29UL, 30UL, 31UL, 32UL, 33UL, 34UL, 35UL, 36UL, 37UL>"}},{"pid":712215,"tid":712215,"ph":"X","ts":58396,"dur":2187,"name":"InstantiateFunction","args":{"detail":"mp::apply<type_list, mp::array<mp::meta_t, sizeof...(Ts) - 12UL>{{&info, &info, &info, &info, &info, &info, &info, &info, &info, &info, ...}}>"}},{"pid":712215,"tid":712215,"ph":"X","ts":60907,"dur":597,"name":"InstantiateFunction","args":{"detail":"drop_impl<13UL, x<0>, x<1>, x<2>, x<3>, x<4>, x<5>, x<6>, x<7>, x<8>, x<9>, x<10>, x<11>, x<12>, x<13>, x<14>, x<15>, x<16>, x<17>, x<18>, x<19>, x<20>, x<21>, x<22>, x<23>, x<24>, x<25>, x<26>, x<27>, x<28>, x<29>, x<30>, x<31>, x<32>, x<33>, x<34>, x<35>, x<36>, x<37>, x<38>, x<39>, x<40>, x<41>, x<42>, x<43>, x<44>, x<45>, x<46>, x<47>, x<48>, x<49>>"}},{"pid":712215,"tid":712215,"ph":"X","ts":62310,"dur":1545,"name":"InstantiateFunction","args":{"detail":"mp::apply()::(anonymous class)::operator()<0UL, 1UL, 2UL, 3UL, 4UL, 5UL, 6UL, 7UL, 8UL, 9UL, 10UL, 11UL, 12UL, 13UL, 14UL, 15UL, 16UL, 17UL, 18UL, 19UL, 20UL, 21UL, 22UL, 23UL, 24UL, 25UL, 26UL, 27UL, 28UL, 29UL, 30UL, 31UL, 32UL, 33UL, 34UL, 35UL, 36UL>"}},{"pid":712215,"tid":712215,"ph":"X","ts":61840,"dur":2133,"name":"InstantiateFunction","args":{"detail":"mp::apply<type_list, mp::array<mp::meta_t, sizeof...(Ts) - 13UL>{{&info, &info, &info, &info, &info, &info, &info, &info, &info, &info, ...}}>"}},{"pid":712215,"tid":712215,"ph":"X","ts":64305,"dur":612,"name":"InstantiateFunction","args":{"detail":"drop_impl<14UL, x<0>, x<1>, x<2>, x<3>, x<4>, x<5>, x<6>, x<7>, x<8>, x<9>, x<10>, x<11>, x<12>, x<13>, x<14>, x<15>, x<16>, x<17>, x<18>, x<19>, x<20>, x<21>, x<22>, x<23>, x<24>, x<25>, x<26>, x<27>, x<28>, x<29>, x<30>, x<31>, x<32>, x<33>, x<34>, x<35>, x<36>, x<37>, x<38>, x<39>, x<40>, x<41>, x<42>, x<43>, x<44>, x<45>, x<46>, x<47>, x<48>, x<49>>"}},{"pid":712215,"tid":712215,"ph":"X","ts":65696,"dur":1539,"name":"InstantiateFunction","args":{"detail":"mp::apply()::(anonymous class)::operator()<0UL, 1UL, 2UL, 3UL, 4UL, 5UL, 6UL, 7UL, 8UL, 9UL, 10UL, 11UL, 12UL, 13UL, 14UL, 15UL, 16UL, 17UL, 18UL, 19UL, 20UL, 21UL, 22UL, 23UL, 24UL, 25UL, 26UL, 27UL, 28UL, 29UL, 30UL, 31UL, 32UL, 33UL, 34UL, 35UL>"}},{"pid":712215,"tid":712215,"ph":"X","ts":65250,"dur":2093,"name":"InstantiateFunction","args":{"detail":"mp::apply<type_list, mp::array<mp::meta_t, sizeof...(Ts) - 14UL>{{&info, &info, &info, &info, &info, &info, &info, &info, &info, &info, ...}}>"}},{"pid":712215,"tid":712215,"ph":"X","ts":67675,"dur":631,"name":"InstantiateFunction","args":{"detail":"drop_impl<15UL, x<0>, x<1>, x<2>, x<3>, x<4>, x<5>, x<6>, x<7>, x<8>, x<9>, x<10>, x<11>, x<12>, x<13>, x<14>, x<15>, x<16>, x<17>, x<18>, x<19>, x<20>, x<21>, x<22>, x<23>, x<24>, x<25>, x<26>, x<27>, x<28>, x<29>, x<30>, x<31>, x<32>, x<33>, x<34>, x<35>, x<36>, x<37>, x<38>, x<39>, x<40>, x<41>, x<42>, x<43>, x<44>, x<45>, x<46>, x<47>, x<48>, x<49>>"}},{"pid":712215,"tid":712215,"ph":"X","ts":69086,"dur":1506,"name":"InstantiateFunction","args":{"detail":"mp::apply()::(anonymous class)::operator()<0UL, 1UL, 2UL, 3UL, 4UL, 5UL, 6UL, 7UL, 8UL, 9UL, 10UL, 11UL, 12UL, 13UL, 14UL, 15UL, 16UL, 17UL, 18UL, 19UL, 20UL, 21UL, 22UL, 23UL, 24UL, 25UL, 26UL, 27UL, 28UL, 29UL, 30UL, 31UL, 32UL, 33UL, 34UL>"}},{"pid":712215,"tid":712215,"ph":"X","ts":68638,"dur":2060,"name":"InstantiateFunction","args":{"detail":"mp::apply<type_list, mp::array<mp::meta_t, sizeof...(Ts) - 15UL>{{&info, &info, &info, &info, &info, &info, &info, &info, &info, &info, ...}}>"}},{"pid":712215,"tid":712215,"ph":"X","ts":71021,"dur":663,"name":"InstantiateFunction","args":{"detail":"drop_impl<16UL, x<0>, x<1>, x<2>, x<3>, x<4>, x<5>, x<6>, x<7>, x<8>, x<9>, x<10>, x<11>, x<12>, x<13>, x<14>, x<15>, x<16>, x<17>, x<18>, x<19>, x<20>, x<21>, x<22>, x<23>, x<24>, x<25>, x<26>, x<27>, x<28>, x<29>, x<30>, x<31>, x<32>, x<33>, x<34>, x<35>, x<36>, x<37>, x<38>, x<39>, x<40>, x<41>, x<42>, x<43>, x<44>, x<45>, x<46>, x<47>, x<48>, x<49>>"}},{"pid":712215,"tid":712215,"ph":"X","ts":72440,"dur":1456,"name":"InstantiateFunction","args":{"detail":"mp::apply()::(anonymous class)::operator()<0UL, 1UL, 2UL, 3UL, 4UL, 5UL, 6UL, 7UL, 8UL, 9UL, 10UL, 11UL, 12UL, 13UL, 14UL, 15UL, 16UL, 17UL, 18UL, 19UL, 20UL, 21UL, 22UL, 23UL, 24UL, 25UL, 26UL, 27UL, 28UL, 29UL, 30UL, 31UL, 32UL, 33UL>"}},{"pid":712215,"tid":712215,"ph":"X","ts":72004,"dur":1998,"name":"InstantiateFunction","args":{"detail":"mp::apply<type_list, mp::array<mp::meta_t, sizeof...(Ts) - 16UL>{{&info, &info, &info, &info, &info, &info, &info, &info, &info, &info, ...}}>"}},{"pid":712215,"tid":712215,"ph":"X","ts":74331,"dur":588,"name":"InstantiateFunction","args":{"detail":"drop_impl<17UL, x<0>, x<1>, x<2>, x<3>, x<4>, x<5>, x<6>, x<7>, x<8>, x<9>, x<10>, x<11>, x<12>, x<13>, x<14>, x<15>, x<16>, x<17>, x<18>, x<19>, x<20>, x<21>, x<22>, x<23>, x<24>, x<25>, x<26>, x<27>, x<28>, x<29>, x<30>, x<31>, x<32>, x<33>, x<34>, x<35>, x<36>, x<37>, x<38>, x<39>, x<40>, x<41>, x<42>, x<43>, x<44>, x<45>, x<46>, x<47>, x<48>, x<49>>"}},{"pid":712215,"tid":712215,"ph":"X","ts":75687,"dur":1416,"name":"InstantiateFunction","args":{"detail":"mp::apply()::(anonymous class)::operator()<0UL, 1UL, 2UL, 3UL, 4UL, 5UL, 6UL, 7UL, 8UL, 9UL, 10UL, 11UL, 12UL, 13UL, 14UL, 15UL, 16UL, 17UL, 18UL, 19UL, 20UL, 21UL, 22UL, 23UL, 24UL, 25UL, 26UL, 27UL, 28UL, 29UL, 30UL, 31UL, 32UL>"}},{"pid":712215,"tid":712215,"ph":"X","ts":75229,"dur":1977,"name":"InstantiateFunction","args":{"detail":"mp::apply<type_list, mp::array<mp::meta_t, sizeof...(Ts) - 17UL>{{&info, &info, &info, &info, &info, &info, &info, &info, &info, &info, ...}}>"}},{"pid":712215,"tid":712215,"ph":"X","ts":77527,"dur":615,"name":"InstantiateFunction","args":{"detail":"drop_impl<18UL, x<0>, x<1>, x<2>, x<3>, x<4>, x<5>, x<6>, x<7>, x<8>, x<9>, x<10>, x<11>, x<12>, x<13>, x<14>, x<15>, x<16>, x<17>, x<18>, x<19>, x<20>, x<21>, x<22>, x<23>, x<24>, x<25>, x<26>, x<27>, x<28>, x<29>, x<30>, x<31>, x<32>, x<33>, x<34>, x<35>, x<36>, x<37>, x<38>, x<39>, x<40>, x<41>, x<42>, x<43>, x<44>, x<45>, x<46>, x<47>, x<48>, x<49>>"}},{"pid":712215,"tid":712215,"ph":"X","ts":78891,"dur":1392,"name":"InstantiateFunction","args":{"detail":"mp::apply()::(anonymous class)::operator()<0UL, 1UL, 2UL, 3UL, 4UL, 5UL, 6UL, 7UL, 8UL, 9UL, 10UL, 11UL, 12UL, 13UL, 14UL, 15UL, 16UL, 17UL, 18UL, 19UL, 20UL, 21UL, 22UL, 23UL, 24UL, 25UL, 26UL, 27UL, 28UL, 29UL, 30UL, 31UL>"}},{"pid":712215,"tid":712215,"ph":"X","ts":78458,"dur":1924,"name":"InstantiateFunction","args":{"detail":"mp::apply<type_list, mp::array<mp::meta_t, sizeof...(Ts) - 18UL>{{&info, &info, &info, &info, &info, &info, &info, &info, &info, &info, ...}}>"}},{"pid":712215,"tid":712215,"ph":"X","ts":80704,"dur":591,"name":"InstantiateFunction","args":{"detail":"drop_impl<19UL, x<0>, x<1>, x<2>, x<3>, x<4>, x<5>, x<6>, x<7>, x<8>, x<9>, x<10>, x<11>, x<12>, x<13>, x<14>, x<15>, x<16>, x<17>, x<18>, x<19>, x<20>, x<21>, x<22>, x<23>, x<24>, x<25>, x<26>, x<27>, x<28>, x<29>, x<30>, x<31>, x<32>, x<33>, x<34>, x<35>, x<36>, x<37>, x<38>, x<39>, x<40>, x<41>, x<42>, x<43>, x<44>, x<45>, x<46>, x<47>, x<48>, x<49>>"}},{"pid":712215,"tid":712215,"ph":"X","ts":82010,"dur":1353,"name":"InstantiateFunction","args":{"detail":"mp::apply()::(anonymous class)::operator()<0UL, 1UL, 2UL, 3UL, 4UL, 5UL, 6UL, 7UL, 8UL, 9UL, 10UL, 11UL, 12UL, 13UL, 14UL, 15UL, 16UL, 17UL, 18UL, 19UL, 20UL, 21UL, 22UL, 23UL, 24UL, 25UL, 26UL, 27UL, 28UL, 29UL, 30UL>"}},{"pid":712215,"tid":712215,"ph":"X","ts":81598,"dur":1864,"name":"InstantiateFunction","args":{"detail":"mp::apply<type_list, mp::array<mp::meta_t, sizeof...(Ts) - 19UL>{{&info, &info, &info, &info, &info, &info, &info, &info, &info, &info, ...}}>"}},{"pid":712215,"tid":712215,"ph":"X","ts":83797,"dur":601,"name":"InstantiateFunction","args":{"detail":"drop_impl<20UL, x<0>, x<1>, x<2>, x<3>, x<4>, x<5>, x<6>, x<7>, x<8>, x<9>, x<10>, x<11>, x<12>, x<13>, x<14>, x<15>, x<16>, x<17>, x<18>, x<19>, x<20>, x<21>, x<22>, x<23>, x<24>, x<25>, x<26>, x<27>, x<28>, x<29>, x<30>, x<31>, x<32>, x<33>, x<34>, x<35>, x<36>, x<37>, x<38>, x<39>, x<40>, x<41>, x<42>, x<43>, x<44>, x<45>, x<46>, x<47>, x<48>, x<49>>"}},{"pid":712215,"tid":712215,"ph":"X","ts":85123,"dur":1307,"name":"InstantiateFunction","args":{"detail":"mp::apply()::(anonymous class)::operator()<0UL, 1UL, 2UL, 3UL, 4UL, 5UL, 6UL, 7UL, 8UL, 9UL, 10UL, 11UL, 12UL, 13UL, 14UL, 15UL, 16UL, 17UL, 18UL, 19UL, 20UL, 21UL, 22UL, 23UL, 24UL, 25UL, 26UL, 27UL, 28UL, 29UL>"}},{"pid":712215,"tid":712215,"ph":"X","ts":84698,"dur":1829,"name":"InstantiateFunction","args":{"detail":"mp::apply<type_list, mp::array<mp::meta_t, sizeof...(Ts) - 20UL>{{&info, &info, &info, &info, &info, &info, &info, &info, &info, &info, ...}}>"}},{"pid":712215,"tid":712215,"ph":"X","ts":87079,"dur":616,"name":"InstantiateFunction","args":{"detail":"drop_impl<21UL, x<0>, x<1>, x<2>, x<3>, x<4>, x<5>, x<6>, x<7>, x<8>, x<9>, x<10>, x<11>, x<12>, x<13>, x<14>, x<15>, x<16>, x<17>, x<18>, x<19>, x<20>, x<21>, x<22>, x<23>, x<24>, x<25>, x<26>, x<27>, x<28>, x<29>, x<30>, x<31>, x<32>, x<33>, x<34>, x<35>, x<36>, x<37>, x<38>, x<39>, x<40>, x<41>, x<42>, x<43>, x<44>, x<45>, x<46>, x<47>, x<48>, x<49>>"}},{"pid":712215,"tid":712215,"ph":"X","ts":88407,"dur":1276,"name":"InstantiateFunction","args":{"detail":"mp::apply()::(anonymous class)::operator()<0UL, 1UL, 2UL, 3UL, 4UL, 5UL, 6UL, 7UL, 8UL, 9UL, 10UL, 11UL, 12UL, 13UL, 14UL, 15UL, 16UL, 17UL, 18UL, 19UL, 20UL, 21UL, 22UL, 23UL, 24UL, 25UL, 26UL, 27UL, 28UL>"}},{"pid":712215,"tid":712215,"ph":"X","ts":87990,"dur":1790,"name":"InstantiateFunction","args":{"detail":"mp::apply<type_list, mp::array<mp::meta_t, sizeof...(Ts) - 21UL>{{&info, &info, &info, &info, &info, &info, &info, &info, &info, &info, ...}}>"}},{"pid":712215,"tid":712215,"ph":"X","ts":90103,"dur":616,"name":"InstantiateFunction","args":{"detail":"drop_impl<22UL, x<0>, x<1>, x<2>, x<3>, x<4>, x<5>, x<6>, x<7>, x<8>, x<9>, x<10>, x<11>, x<12>, x<13>, x<14>, x<15>, x<16>, x<17>, x<18>, x<19>, x<20>, x<21>, x<22>, x<23>, x<24>, x<25>, x<26>, x<27>, x<28>, x<29>, x<30>, x<31>, x<32>, x<33>, x<34>, x<35>, x<36>, x<37>, x<38>, x<39>, x<40>, x<41>, x<42>, x<43>, x<44>, x<45>, x<46>, x<47>, x<48>, x<49>>"}},{"pid":712215,"tid":712215,"ph":"X","ts":91416,"dur":1234,"name":"InstantiateFunction","args":{"detail":"mp::apply()::(anonymous class)::operator()<0UL, 1UL, 2UL, 3UL, 4UL, 5UL, 6UL, 7UL, 8UL, 9UL, 10UL, 11UL, 12UL, 13UL, 14UL, 15UL, 16UL, 17UL, 18UL, 19UL, 20UL, 21UL, 22UL, 23UL, 24UL, 25UL, 26UL, 27UL>"}},{"pid":712215,"tid":712215,"ph":"X","ts":91004,"dur":1738,"name":"InstantiateFunction","args":{"detail":"mp::apply<type_list, mp::array<mp::meta_t, sizeof...(Ts) - 22UL>{{&info, &info, &info, &info, &info, &info, &info, &info, &info, &info, ...}}>"}},{"pid":712215,"tid":712215,"ph":"X","ts":93062,"dur":599,"name":"InstantiateFunction","args":{"detail":"drop_impl<23UL, x<0>, x<1>, x<2>, x<3>, x<4>, x<5>, x<6>, x<7>, x<8>, x<9>, x<10>, x<11>, x<12>, x<13>, x<14>, x<15>, x<16>, x<17>, x<18>, x<19>, x<20>, x<21>, x<22>, x<23>, x<24>, x<25>, x<26>, x<27>, x<28>, x<29>, x<30>, x<31>, x<32>, x<33>, x<34>, x<35>, x<36>, x<37>, x<38>, x<39>, x<40>, x<41>, x<42>, x<43>, x<44>, x<45>, x<46>, x<47>, x<48>, x<49>>"}},{"pid":712215,"tid":712215,"ph":"X","ts":94366,"dur":1217,"name":"InstantiateFunction","args":{"detail":"mp::apply()::(anonymous class)::operator()<0UL, 1UL, 2UL, 3UL, 4UL, 5UL, 6UL, 7UL, 8UL, 9UL, 10UL, 11UL, 12UL, 13UL, 14UL, 15UL, 16UL, 17UL, 18UL, 19UL, 20UL, 21UL, 22UL, 23UL, 24UL, 25UL, 26UL>"}},{"pid":712215,"tid":712215,"ph":"X","ts":93945,"dur":1730,"name":"InstantiateFunction","args":{"detail":"mp::apply<type_list, mp::array<mp::meta_t, sizeof...(Ts) - 23UL>{{&info, &info, &info, &info, &info, &info, &info, &info, &info, &info, ...}}>"}},{"pid":712215,"tid":712215,"ph":"X","ts":96004,"dur":605,"name":"InstantiateFunction","args":{"detail":"drop_impl<24UL, x<0>, x<1>, x<2>, x<3>, x<4>, x<5>, x<6>, x<7>, x<8>, x<9>, x<10>, x<11>, x<12>, x<13>, x<14>, x<15>, x<16>, x<17>, x<18>, x<19>, x<20>, x<21>, x<22>, x<23>, x<24>, x<25>, x<26>, x<27>, x<28>, x<29>, x<30>, x<31>, x<32>, x<33>, x<34>, x<35>, x<36>, x<37>, x<38>, x<39>, x<40>, x<41>, x<42>, x<43>, x<44>, x<45>, x<46>, x<47>, x<48>, x<49>>"}},{"pid":712215,"tid":712215,"ph":"X","ts":97283,"dur":1128,"name":"InstantiateFunction","args":{"detail":"mp::apply()::(anonymous class)::operator()<0UL, 1UL, 2UL, 3UL, 4UL, 5UL, 6UL, 7UL, 8UL, 9UL, 10UL, 11UL, 12UL, 13UL, 14UL, 15UL, 16UL, 17UL, 18UL, 19UL, 20UL, 21UL, 22UL, 23UL, 24UL, 25UL>"}},{"pid":712215,"tid":712215,"ph":"X","ts":96886,"dur":1609,"name":"InstantiateFunction","args":{"detail":"mp::apply<type_list, mp::array<mp::meta_t, sizeof...(Ts) - 24UL>{{&info, &info, &info, &info, &info, &info, &info, &info, &info, &info, ...}}>"}},{"pid":712215,"tid":712215,"ph":"X","ts":98823,"dur":599,"name":"InstantiateFunction","args":{"detail":"drop_impl<25UL, x<0>, x<1>, x<2>, x<3>, x<4>, x<5>, x<6>, x<7>, x<8>, x<9>, x<10>, x<11>, x<12>, x<13>, x<14>, x<15>, x<16>, x<17>, x<18>, x<19>, x<20>, x<21>, x<22>, x<23>, x<24>, x<25>, x<26>, x<27>, x<28>, x<29>, x<30>, x<31>, x<32>, x<33>, x<34>, x<35>, x<36>, x<37>, x<38>, x<39>, x<40>, x<41>, x<42>, x<43>, x<44>, x<45>, x<46>, x<47>, x<48>, x<49>>"}},{"pid":712215,"tid":712215,"ph":"X","ts":100097,"dur":1112,"name":"InstantiateFunction","args":{"detail":"mp::apply()::(anonymous class)::operator()<0UL, 1UL, 2UL, 3UL, 4UL, 5UL, 6UL, 7UL, 8UL, 9UL, 10UL, 11UL, 12UL, 13UL, 14UL, 15UL, 16UL, 17UL, 18UL, 19UL, 20UL, 21UL, 22UL, 23UL, 24UL>"}},{"pid":712215,"tid":712215,"ph":"X","ts":99705,"dur":1590,"name":"InstantiateFunction","args":{"detail":"mp::apply<type_list, mp::array<mp::meta_t, sizeof...(Ts) - 25UL>{{&info, &info, &info, &info, &info, &info, &info, &info, &info, &info, ...}}>"}},{"pid":712215,"tid":712215,"ph":"X","ts":101615,"dur":586,"name":"InstantiateFunction","args":{"detail":"drop_impl<26UL, x<0>, x<1>, x<2>, x<3>, x<4>, x<5>, x<6>, x<7>, x<8>, x<9>, x<10>, x<11>, x<12>, x<13>, x<14>, x<15>, x<16>, x<17>, x<18>, x<19>, x<20>, x<21>, x<22>, x<23>, x<24>, x<25>, x<26>, x<27>, x<28>, x<29>, x<30>, x<31>, x<32>, x<33>, x<34>, x<35>, x<36>, x<37>, x<38>, x<39>, x<40>, x<41>, x<42>, x<43>, x<44>, x<45>, x<46>, x<47>, x<48>, x<49>>"}},{"pid":712215,"tid":712215,"ph":"X","ts":102862,"dur":1118,"name":"InstantiateFunction","args":{"detail":"mp::apply()::(anonymous class)::operator()<0UL, 1UL, 2UL, 3UL, 4UL, 5UL, 6UL, 7UL, 8UL, 9UL, 10UL, 11UL, 12UL, 13UL, 14UL, 15UL, 16UL, 17UL, 18UL, 19UL, 20UL, 21UL, 22UL, 23UL>"}},{"pid":712215,"tid":712215,"ph":"X","ts":102473,"dur":1599,"name":"InstantiateFunction","args":{"detail":"mp::apply<type_list, mp::array<mp::meta_t, sizeof...(Ts) - 26UL>{{&info, &info, &info, &info, &info, &info, &info, &info, &info, &info, ...}}>"}},{"pid":712215,"tid":712215,"ph":"X","ts":104390,"dur":635,"name":"InstantiateFunction","args":{"detail":"drop_impl<27UL, x<0>, x<1>, x<2>, x<3>, x<4>, x<5>, x<6>, x<7>, x<8>, x<9>, x<10>, x<11>, x<12>, x<13>, x<14>, x<15>, x<16>, x<17>, x<18>, x<19>, x<20>, x<21>, x<22>, x<23>, x<24>, x<25>, x<26>, x<27>, x<28>, x<29>, x<30>, x<31>, x<32>, x<33>, x<34>, x<35>, x<36>, x<37>, x<38>, x<39>, x<40>, x<41>, x<42>, x<43>, x<44>, x<45>, x<46>, x<47>, x<48>, x<49>>"}},{"pid":712215,"tid":712215,"ph":"X","ts":105675,"dur":1032,"name":"InstantiateFunction","args":{"detail":"mp::apply()::(anonymous class)::operator()<0UL, 1UL, 2UL, 3UL, 4UL, 5UL, 6UL, 7UL, 8UL, 9UL, 10UL, 11UL, 12UL, 13UL, 14UL, 15UL, 16UL, 17UL, 18UL, 19UL, 20UL, 21UL, 22UL>"}},{"pid":712215,"tid":712215,"ph":"X","ts":105284,"dur":1505,"name":"InstantiateFunction","args":{"detail":"mp::apply<type_list, mp::array<mp::meta_t, sizeof...(Ts) - 27UL>{{&info, &info, &info, &info, &info, &info, &info, &info, &info, &info, ...}}>"}},{"pid":712215,"tid":712215,"ph":"X","ts":107116,"dur":599,"name":"InstantiateFunction","args":{"detail":"drop_impl<28UL, x<0>, x<1>, x<2>, x<3>, x<4>, x<5>, x<6>, x<7>, x<8>, x<9>, x<10>, x<11>, x<12>, x<13>, x<14>, x<15>, x<16>, x<17>, x<18>, x<19>, x<20>, x<21>, x<22>, x<23>, x<24>, x<25>, x<26>, x<27>, x<28>, x<29>, x<30>, x<31>, x<32>, x<33>, x<34>, x<35>, x<36>, x<37>, x<38>, x<39>, x<40>, x<41>, x<42>, x<43>, x<44>, x<45>, x<46>, x<47>, x<48>, x<49>>"}},{"pid":712215,"tid":712215,"ph":"X","ts":108356,"dur":979,"name":"InstantiateFunction","args":{"detail":"mp::apply()::(anonymous class)::operator()<0UL, 1UL, 2UL, 3UL, 4UL, 5UL, 6UL, 7UL, 8UL, 9UL, 10UL, 11UL, 12UL, 13UL, 14UL, 15UL, 16UL, 17UL, 18UL, 19UL, 20UL, 21UL>"}},{"pid":712215,"tid":712215,"ph":"X","ts":107970,"dur":1441,"name":"InstantiateFunction","args":{"detail":"mp::apply<type_list, mp::array<mp::meta_t, sizeof...(Ts) - 28UL>{{&info, &info, &info, &info, &info, &info, &info, &info, &info, &info, ...}}>"}},{"pid":712215,"tid":712215,"ph":"X","ts":109732,"dur":616,"name":"InstantiateFunction","args":{"detail":"drop_impl<29UL, x<0>, x<1>, x<2>, x<3>, x<4>, x<5>, x<6>, x<7>, x<8>, x<9>, x<10>, x<11>, x<12>, x<13>, x<14>, x<15>, x<16>, x<17>, x<18>, x<19>, x<20>, x<21>, x<22>, x<23>, x<24>, x<25>, x<26>, x<27>, x<28>, x<29>, x<30>, x<31>, x<32>, x<33>, x<34>, x<35>, x<36>, x<37>, x<38>, x<39>, x<40>, x<41>, x<42>, x<43>, x<44>, x<45>, x<46>, x<47>, x<48>, x<49>>"}},{"pid":712215,"tid":712215,"ph":"X","ts":110954,"dur":947,"name":"InstantiateFunction","args":{"detail":"mp::apply()::(anonymous class)::operator()<0UL, 1UL, 2UL, 3UL, 4UL, 5UL, 6UL, 7UL, 8UL, 9UL, 10UL, 11UL, 12UL, 13UL, 14UL, 15UL, 16UL, 17UL, 18UL, 19UL, 20UL>"}},{"pid":712215,"tid":712215,"ph":"X","ts":110596,"dur":1382,"name":"InstantiateFunction","args":{"detail":"mp::apply<type_list, mp::array<mp::meta_t, sizeof...(Ts) - 29UL>{{&info, &info, &info, &info, &info, &info, &info, &info, &info, &info, ...}}>"}},{"pid":712215,"tid":712215,"ph":"X","ts":112296,"dur":608,"name":"InstantiateFunction","args":{"detail":"drop_impl<30UL, x<0>, x<1>, x<2>, x<3>, x<4>, x<5>, x<6>, x<7>, x<8>, x<9>, x<10>, x<11>, x<12>, x<13>, x<14>, x<15>, x<16>, x<17>, x<18>, x<19>, x<20>, x<21>, x<22>, x<23>, x<24>, x<25>, x<26>, x<27>, x<28>, x<29>, x<30>, x<31>, x<32>, x<33>, x<34>, x<35>, x<36>, x<37>, x<38>, x<39>, x<40>, x<41>, x<42>, x<43>, x<44>, x<45>, x<46>, x<47>, x<48>, x<49>>"}},{"pid":712215,"tid":712215,"ph":"X","ts":113511,"dur":904,"name":"InstantiateFunction","args":{"detail":"mp::apply()::(anonymous class)::operator()<0UL, 1UL, 2UL, 3UL, 4UL, 5UL, 6UL, 7UL, 8UL, 9UL, 10UL, 11UL, 12UL, 13UL, 14UL, 15UL, 16UL, 17UL, 18UL, 19UL>"}},{"pid":712215,"tid":712215,"ph":"X","ts":113149,"dur":1338,"name":"InstantiateFunction","args":{"detail":"mp::apply<type_list, mp::array<mp::meta_t, sizeof...(Ts) - 30UL>{{&info, &info, &info, &info, &info, &info, &info, &info, &info, &info, ...}}>"}},{"pid":712215,"tid":712215,"ph":"X","ts":114808,"dur":606,"name":"InstantiateFunction","args":{"detail":"drop_impl<31UL, x<0>, x<1>, x<2>, x<3>, x<4>, x<5>, x<6>, x<7>, x<8>, x<9>, x<10>, x<11>, x<12>, x<13>, x<14>, x<15>, x<16>, x<17>, x<18>, x<19>, x<20>, x<21>, x<22>, x<23>, x<24>, x<25>, x<26>, x<27>, x<28>, x<29>, x<30>, x<31>, x<32>, x<33>, x<34>, x<35>, x<36>, x<37>, x<38>, x<39>, x<40>, x<41>, x<42>, x<43>, x<44>, x<45>, x<46>, x<47>, x<48>, x<49>>"}},{"pid":712215,"tid":712215,"ph":"X","ts":116038,"dur":862,"name":"InstantiateFunction","args":{"detail":"mp::apply()::(anonymous class)::operator()<0UL, 1UL, 2UL, 3UL, 4UL, 5UL, 6UL, 7UL, 8UL, 9UL, 10UL, 11UL, 12UL, 13UL, 14UL, 15UL, 16UL, 17UL, 18UL>"}},{"pid":712215,"tid":712215,"ph":"X","ts":115667,"dur":1307,"name":"InstantiateFunction","args":{"detail":"mp::apply<type_list, mp::array<mp::meta_t, sizeof...(Ts) - 31UL>{{&info, &info, &info, &info, &info, &info, &info, &info, &info, &info, ...}}>"}},{"pid":712215,"tid":712215,"ph":"X","ts":117303,"dur":590,"name":"InstantiateFunction","args":{"detail":"drop_impl<32UL, x<0>, x<1>, x<2>, x<3>, x<4>, x<5>, x<6>, x<7>, x<8>, x<9>, x<10>, x<11>, x<12>, x<13>, x<14>, x<15>, x<16>, x<17>, x<18>, x<19>, x<20>, x<21>, x<22>, x<23>, x<24>, x<25>, x<26>, x<27>, x<28>, x<29>, x<30>, x<31>, x<32>, x<33>, x<34>, x<35>, x<36>, x<37>, x<38>, x<39>, x<40>, x<41>, x<42>, x<43>, x<44>, x<45>, x<46>, x<47>, x<48>, x<49>>"}},{"pid":712215,"tid":712215,"ph":"X","ts":118501,"dur":829,"name":"InstantiateFunction","args":{"detail":"mp::apply()::(anonymous class)::operator()<0UL, 1UL, 2UL, 3UL, 4UL, 5UL, 6UL, 7UL, 8UL, 9UL, 10UL, 11UL, 12UL, 13UL, 14UL, 15UL, 16UL, 17UL>"}},{"pid":712215,"tid":712215,"ph":"X","ts":118127,"dur":1273,"name":"InstantiateFunction","args":{"detail":"mp::apply<type_list, mp::array<mp::meta_t, sizeof...(Ts) - 32UL>{{&info, &info, &info, &info, &info, &info, &info, &info, &info, &info, ...}}>"}},{"pid":712215,"tid":712215,"ph":"X","ts":119735,"dur":593,"name":"InstantiateFunction","args":{"detail":"drop_impl<33UL, x<0>, x<1>, x<2>, x<3>, x<4>, x<5>, x<6>, x<7>, x<8>, x<9>, x<10>, x<11>, x<12>, x<13>, x<14>, x<15>, x<16>, x<17>, x<18>, x<19>, x<20>, x<21>, x<22>, x<23>, x<24>, x<25>, x<26>, x<27>, x<28>, x<29>, x<30>, x<31>, x<32>, x<33>, x<34>, x<35>, x<36>, x<37>, x<38>, x<39>, x<40>, x<41>, x<42>, x<43>, x<44>, x<45>, x<46>, x<47>, x<48>, x<49>>"}},{"pid":712215,"tid":712215,"ph":"X","ts":120896,"dur":790,"name":"InstantiateFunction","args":{"detail":"mp::apply()::(anonymous class)::operator()<0UL, 1UL, 2UL, 3UL, 4UL, 5UL, 6UL, 7UL, 8UL, 9UL, 10UL, 11UL, 12UL, 13UL, 14UL, 15UL, 16UL>"}},{"pid":712215,"tid":712215,"ph":"X","ts":120551,"dur":1201,"name":"InstantiateFunction","args":{"detail":"mp::apply<type_list, mp::array<mp::meta_t, sizeof...(Ts) - 33UL>{{&info, &info, &info, &info, &info, &info, &info, &info, &info, &info, ...}}>"}},{"pid":712215,"tid":712215,"ph":"X","ts":122088,"dur":643,"name":"InstantiateFunction","args":{"detail":"drop_impl<34UL, x<0>, x<1>, x<2>, x<3>, x<4>, x<5>, x<6>, x<7>, x<8>, x<9>, x<10>, x<11>, x<12>, x<13>, x<14>, x<15>, x<16>, x<17>, x<18>, x<19>, x<20>, x<21>, x<22>, x<23>, x<24>, x<25>, x<26>, x<27>, x<28>, x<29>, x<30>, x<31>, x<32>, x<33>, x<34>, x<35>, x<36>, x<37>, x<38>, x<39>, x<40>, x<41>, x<42>, x<43>, x<44>, x<45>, x<46>, x<47>, x<48>, x<49>>"}},{"pid":712215,"tid":712215,"ph":"X","ts":123279,"dur":769,"name":"InstantiateFunction","args":{"detail":"mp::apply()::(anonymous class)::operator()<0UL, 1UL, 2UL, 3UL, 4UL, 5UL, 6UL, 7UL, 8UL, 9UL, 10UL, 11UL, 12UL, 13UL, 14UL, 15UL>"}},{"pid":712215,"tid":712215,"ph":"X","ts":122948,"dur":1163,"name":"InstantiateFunction","args":{"detail":"mp::apply<type_list, mp::array<mp::meta_t, sizeof...(Ts) - 34UL>{{&info, &info, &info, &info, &info, &info, &info, &info, &info, &info, ...}}>"}},{"pid":712215,"tid":712215,"ph":"X","ts":124435,"dur":615,"name":"InstantiateFunction","args":{"detail":"drop_impl<35UL, x<0>, x<1>, x<2>, x<3>, x<4>, x<5>, x<6>, x<7>, x<8>, x<9>, x<10>, x<11>, x<12>, x<13>, x<14>, x<15>, x<16>, x<17>, x<18>, x<19>, x<20>, x<21>, x<22>, x<23>, x<24>, x<25>, x<26>, x<27>, x<28>, x<29>, x<30>, x<31>, x<32>, x<33>, x<34>, x<35>, x<36>, x<37>, x<38>, x<39>, x<40>, x<41>, x<42>, x<43>, x<44>, x<45>, x<46>, x<47>, x<48>, x<49>>"}},{"pid":712215,"tid":712215,"ph":"X","ts":125608,"dur":722,"name":"InstantiateFunction","args":{"detail":"mp::apply()::(anonymous class)::operator()<0UL, 1UL, 2UL, 3UL, 4UL, 5UL, 6UL, 7UL, 8UL, 9UL, 10UL, 11UL, 12UL, 13UL, 14UL>"}},{"pid":712215,"tid":712215,"ph":"X","ts":125269,"dur":1121,"name":"InstantiateFunction","args":{"detail":"mp::apply<type_list, mp::array<mp::meta_t, sizeof...(Ts) - 35UL>{{&info, &info, &info, &info, &info, &info, &info, &info, &info, &info, ...}}>"}},{"pid":712215,"tid":712215,"ph":"X","ts":126719,"dur":704,"name":"InstantiateFunction","args":{"detail":"drop_impl<36UL, x<0>, x<1>, x<2>, x<3>, x<4>, x<5>, x<6>, x<7>, x<8>, x<9>, x<10>, x<11>, x<12>, x<13>, x<14>, x<15>, x<16>, x<17>, x<18>, x<19>, x<20>, x<21>, x<22>, x<23>, x<24>, x<25>, x<26>, x<27>, x<28>, x<29>, x<30>, x<31>, x<32>, x<33>, x<34>, x<35>, x<36>, x<37>, x<38>, x<39>, x<40>, x<41>, x<42>, x<43>, x<44>, x<45>, x<46>, x<47>, x<48>, x<49>>"}},{"pid":712215,"tid":712215,"ph":"X","ts":127974,"dur":677,"name":"InstantiateFunction","args":{"detail":"mp::apply()::(anonymous class)::operator()<0UL, 1UL, 2UL, 3UL, 4UL, 5UL, 6UL, 7UL, 8UL, 9UL, 10UL, 11UL, 12UL, 13UL>"}},{"pid":712215,"tid":712215,"ph":"X","ts":127632,"dur":1080,"name":"InstantiateFunction","args":{"detail":"mp::apply<type_list, mp::array<mp::meta_t, sizeof...(Ts) - 36UL>{{&info, &info, &info, &info, &info, &info, &info, &info, &info, &info, ...}}>"}},{"pid":712215,"tid":712215,"ph":"X","ts":129034,"dur":591,"name":"InstantiateFunction","args":{"detail":"drop_impl<37UL, x<0>, x<1>, x<2>, x<3>, x<4>, x<5>, x<6>, x<7>, x<8>, x<9>, x<10>, x<11>, x<12>, x<13>, x<14>, x<15>, x<16>, x<17>, x<18>, x<19>, x<20>, x<21>, x<22>, x<23>, x<24>, x<25>, x<26>, x<27>, x<28>, x<29>, x<30>, x<31>, x<32>, x<33>, x<34>, x<35>, x<36>, x<37>, x<38>, x<39>, x<40>, x<41>, x<42>, x<43>, x<44>, x<45>, x<46>, x<47>, x<48>, x<49>>"}},{"pid":712215,"tid":712215,"ph":"X","ts":130139,"dur":652,"name":"InstantiateFunction","args":{"detail":"mp::apply()::(anonymous class)::operator()<0UL, 1UL, 2UL, 3UL, 4UL, 5UL, 6UL, 7UL, 8UL, 9UL, 10UL, 11UL, 12UL>"}},{"pid":712215,"tid":712215,"ph":"X","ts":129824,"dur":1024,"name":"InstantiateFunction","args":{"detail":"mp::apply<type_list, mp::array<mp::meta_t, sizeof...(Ts) - 37UL>{{&info, &info, &info, &info, &info, &info, &info, &info, &info, &info, ...}}>"}},{"pid":712215,"tid":712215,"ph":"X","ts":131180,"dur":588,"name":"InstantiateFunction","args":{"detail":"drop_impl<38UL, x<0>, x<1>, x<2>, x<3>, x<4>, x<5>, x<6>, x<7>, x<8>, x<9>, x<10>, x<11>, x<12>, x<13>, x<14>, x<15>, x<16>, x<17>, x<18>, x<19>, x<20>, x<21>, x<22>, x<23>, x<24>, x<25>, x<26>, x<27>, x<28>, x<29>, x<30>, x<31>, x<32>, x<33>, x<34>, x<35>, x<36>, x<37>, x<38>, x<39>, x<40>, x<41>, x<42>, x<43>, x<44>, x<45>, x<46>, x<47>, x<48>, x<49>>"}},{"pid":712215,"tid":712215,"ph":"X","ts":132290,"dur":586,"name":"InstantiateFunction","args":{"detail":"mp::apply()::(anonymous class)::operator()<0UL, 1UL, 2UL, 3UL, 4UL, 5UL, 6UL, 7UL, 8UL, 9UL, 10UL, 11UL>"}},{"pid":712215,"tid":712215,"ph":"X","ts":131968,"dur":1028,"name":"InstantiateFunction","args":{"detail":"mp::apply<type_list, mp::array<mp::meta_t, sizeof...(Ts) - 38UL>{{&info, &info, &info, &info, &info, &info, &info, &info, &info, &info, ...}}>"}},{"pid":712215,"tid":712215,"ph":"X","ts":133324,"dur":650,"name":"InstantiateFunction","args":{"detail":"drop_impl<39UL, x<0>, x<1>, x<2>, x<3>, x<4>, x<5>, x<6>, x<7>, x<8>, x<9>, x<10>, x<11>, x<12>, x<13>, x<14>, x<15>, x<16>, x<17>, x<18>, x<19>, x<20>, x<21>, x<22>, x<23>, x<24>, x<25>, x<26>, x<27>, x<28>, x<29>, x<30>, x<31>, x<32>, x<33>, x<34>, x<35>, x<36>, x<37>, x<38>, x<39>, x<40>, x<41>, x<42>, x<43>, x<44>, x<45>, x<46>, x<47>, x<48>, x<49>>"}},{"pid":712215,"tid":712215,"ph":"X","ts":134521,"dur":571,"name":"InstantiateFunction","args":{"detail":"mp::apply()::(anonymous class)::operator()<0UL, 1UL, 2UL, 3UL, 4UL, 5UL, 6UL, 7UL, 8UL, 9UL, 10UL>"}},{"pid":712215,"tid":712215,"ph":"X","ts":134180,"dur":965,"name":"InstantiateFunction","args":{"detail":"mp::apply<type_list, mp::array<mp::meta_t, sizeof...(Ts) - 39UL>{{&info, &info, &info, &info, &info, &info, &info, &info, &info, &info, ...}}>"}},{"pid":712215,"tid":712215,"ph":"X","ts":135474,"dur":608,"name":"InstantiateFunction","args":{"detail":"drop_impl<40UL, x<0>, x<1>, x<2>, x<3>, x<4>, x<5>, x<6>, x<7>, x<8>, x<9>, x<10>, x<11>, x<12>, x<13>, x<14>, x<15>, x<16>, x<17>, x<18>, x<19>, x<20>, x<21>, x<22>, x<23>, x<24>, x<25>, x<26>, x<27>, x<28>, x<29>, x<30>, x<31>, x<32>, x<33>, x<34>, x<35>, x<36>, x<37>, x<38>, x<39>, x<40>, x<41>, x<42>, x<43>, x<44>, x<45>, x<46>, x<47>, x<48>, x<49>>"}},{"pid":712215,"tid":712215,"ph":"X","ts":136570,"dur":506,"name":"InstantiateFunction","args":{"detail":"mp::apply()::(anonymous class)::operator()<0UL, 1UL, 2UL, 3UL, 4UL, 5UL, 6UL, 7UL, 8UL, 9UL>"}},{"pid":712215,"tid":712215,"ph":"X","ts":136265,"dur":867,"name":"InstantiateFunction","args":{"detail":"mp::apply<type_list, mp::array<mp::meta_t, sizeof...(Ts) - 40UL>{{&info, &info, &info, &info, &info, &info, &info, &info, &info, &info}}>"}},{"pid":712215,"tid":712215,"ph":"X","ts":137454,"dur":600,"name":"InstantiateFunction","args":{"detail":"drop_impl<41UL, x<0>, x<1>, x<2>, x<3>, x<4>, x<5>, x<6>, x<7>, x<8>, x<9>, x<10>, x<11>, x<12>, x<13>, x<14>, x<15>, x<16>, x<17>, x<18>, x<19>, x<20>, x<21>, x<22>, x<23>, x<24>, x<25>, x<26>, x<27>, x<28>, x<29>, x<30>, x<31>, x<32>, x<33>, x<34>, x<35>, x<36>, x<37>, x<38>, x<39>, x<40>, x<41>, x<42>, x<43>, x<44>, x<45>, x<46>, x<47>, x<48>, x<49>>"}},{"pid":712215,"tid":712215,"ph":"X","ts":138232,"dur":847,"name":"InstantiateFunction","args":{"detail":"mp::apply<type_list, mp::array<mp::meta_t, sizeof...(Ts) - 41UL>{{&info, &info, &info, &info, &info, &info, &info, &info, &info}}>"}},{"pid":712215,"tid":712215,"ph":"X","ts":139402,"dur":601,"name":"InstantiateFunction","args":{"detail":"drop_impl<42UL, x<0>, x<1>, x<2>, x<3>, x<4>, x<5>, x<6>, x<7>, x<8>, x<9>, x<10>, x<11>, x<12>, x<13>, x<14>, x<15>, x<16>, x<17>, x<18>, x<19>, x<20>, x<21>, x<22>, x<23>, x<24>, x<25>, x<26>, x<27>, x<28>, x<29>, x<30>, x<31>, x<32>, x<33>, x<34>, x<35>, x<36>, x<37>, x<38>, x<39>, x<40>, x<41>, x<42>, x<43>, x<44>, x<45>, x<46>, x<47>, x<48>, x<49>>"}},{"pid":712215,"tid":712215,"ph":"X","ts":140179,"dur":795,"name":"InstantiateFunction","args":{"detail":"mp::apply<type_list, mp::array<mp::meta_t, sizeof...(Ts) - 42UL>{{&info, &info, &info, &info, &info, &info, &info, &info}}>"}},{"pid":712215,"tid":712215,"ph":"X","ts":141331,"dur":589,"name":"InstantiateFunction","args":{"detail":"drop_impl<43UL, x<0>, x<1>, x<2>, x<3>, x<4>, x<5>, x<6>, x<7>, x<8>, x<9>, x<10>, x<11>, x<12>, x<13>, x<14>, x<15>, x<16>, x<17>, x<18>, x<19>, x<20>, x<21>, x<22>, x<23>, x<24>, x<25>, x<26>, x<27>, x<28>, x<29>, x<30>, x<31>, x<32>, x<33>, x<34>, x<35>, x<36>, x<37>, x<38>, x<39>, x<40>, x<41>, x<42>, x<43>, x<44>, x<45>, x<46>, x<47>, x<48>, x<49>>"}},{"pid":712215,"tid":712215,"ph":"X","ts":142079,"dur":773,"name":"InstantiateFunction","args":{"detail":"mp::apply<type_list, mp::array<mp::meta_t, sizeof...(Ts) - 43UL>{{&info, &info, &info, &info, &info, &info, &info}}>"}},{"pid":712215,"tid":712215,"ph":"X","ts":143175,"dur":586,"name":"InstantiateFunction","args":{"detail":"drop_impl<44UL, x<0>, x<1>, x<2>, x<3>, x<4>, x<5>, x<6>, x<7>, x<8>, x<9>, x<10>, x<11>, x<12>, x<13>, x<14>, x<15>, x<16>, x<17>, x<18>, x<19>, x<20>, x<21>, x<22>, x<23>, x<24>, x<25>, x<26>, x<27>, x<28>, x<29>, x<30>, x<31>, x<32>, x<33>, x<34>, x<35>, x<36>, x<37>, x<38>, x<39>, x<40>, x<41>, x<42>, x<43>, x<44>, x<45>, x<46>, x<47>, x<48>, x<49>>"}},{"pid":712215,"tid":712215,"ph":"X","ts":143929,"dur":672,"name":"InstantiateFunction","args":{"detail":"mp::apply<type_list, mp::array<mp::meta_t, sizeof...(Ts) - 44UL>{{&info, &info, &info, &info, &info, &info}}>"}},{"pid":712215,"tid":712215,"ph":"X","ts":144933,"dur":589,"name":"InstantiateFunction","args":{"detail":"drop_impl<45UL, x<0>, x<1>, x<2>, x<3>, x<4>, x<5>, x<6>, x<7>, x<8>, x<9>, x<10>, x<11>, x<12>, x<13>, x<14>, x<15>, x<16>, x<17>, x<18>, x<19>, x<20>, x<21>, x<22>, x<23>, x<24>, x<25>, x<26>, x<27>, x<28>, x<29>, x<30>, x<31>, x<32>, x<33>, x<34>, x<35>, x<36>, x<37>, x<38>, x<39>, x<40>, x<41>, x<42>, x<43>, x<44>, x<45>, x<46>, x<47>, x<48>, x<49>>"}},{"pid":712215,"tid":712215,"ph":"X","ts":145675,"dur":650,"name":"InstantiateFunction","args":{"detail":"mp::apply<type_list, mp::array<mp::meta_t, sizeof...(Ts) - 45UL>{{&info, &info, &info, &info, &info}}>"}},{"pid":712215,"tid":712215,"ph":"X","ts":146662,"dur":607,"name":"InstantiateFunction","args":{"detail":"drop_impl<46UL, x<0>, x<1>, x<2>, x<3>, x<4>, x<5>, x<6>, x<7>, x<8>, x<9>, x<10>, x<11>, x<12>, x<13>, x<14>, x<15>, x<16>, x<17>, x<18>, x<19>, x<20>, x<21>, x<22>, x<23>, x<24>, x<25>, x<26>, x<27>, x<28>, x<29>, x<30>, x<31>, x<32>, x<33>, x<34>, x<35>, x<36>, x<37>, x<38>, x<39>, x<40>, x<41>, x<42>, x<43>, x<44>, x<45>, x<46>, x<47>, x<48>, x<49>>"}},{"pid":712215,"tid":712215,"ph":"X","ts":147415,"dur":573,"name":"InstantiateFunction","args":{"detail":"mp::apply<type_list, mp::array<mp::meta_t, sizeof...(Ts) - 46UL>{{&info, &info, &info, &info}}>"}},{"pid":712215,"tid":712215,"ph":"X","ts":148307,"dur":598,"name":"InstantiateFunction","args":{"detail":"drop_impl<47UL, x<0>, x<1>, x<2>, x<3>, x<4>, x<5>, x<6>, x<7>, x<8>, x<9>, x<10>, x<11>, x<12>, x<13>, x<14>, x<15>, x<16>, x<17>, x<18>, x<19>, x<20>, x<21>, x<22>, x<23>, x<24>, x<25>, x<26>, x<27>, x<28>, x<29>, x<30>, x<31>, x<32>, x<33>, x<34>, x<35>, x<36>, x<37>, x<38>, x<39>, x<40>, x<41>, x<42>, x<43>, x<44>, x<45>, x<46>, x<47>, x<48>, x<49>>"}},{"pid":712215,"tid":712215,"ph":"X","ts":149053,"dur":569,"name":"InstantiateFunction","args":{"detail":"mp::apply<type_list, mp::array<mp::meta_t, sizeof...(Ts) - 47UL>{{&info, &info, &info}}>"}},{"pid":712215,"tid":712215,"ph":"X","ts":149954,"dur":595,"name":"InstantiateFunction","args":{"detail":"drop_impl<48UL, x<0>, x<1>, x<2>, x<3>, x<4>, x<5>, x<6>, x<7>, x<8>, x<9>, x<10>, x<11>, x<12>, x<13>, x<14>, x<15>, x<16>, x<17>, x<18>, x<19>, x<20>, x<21>, x<22>, x<23>, x<24>, x<25>, x<26>, x<27>, x<28>, x<29>, x<30>, x<31>, x<32>, x<33>, x<34>, x<35>, x<36>, x<37>, x<38>, x<39>, x<40>, x<41>, x<42>, x<43>, x<44>, x<45>, x<46>, x<47>, x<48>, x<49>>"}},{"pid":712215,"tid":712215,"ph":"X","ts":151486,"dur":588,"name":"InstantiateFunction","args":{"detail":"drop_impl<49UL, x<0>, x<1>, x<2>, x<3>, x<4>, x<5>, x<6>, x<7>, x<8>, x<9>, x<10>, x<11>, x<12>, x<13>, x<14>, x<15>, x<16>, x<17>, x<18>, x<19>, x<20>, x<21>, x<22>, x<23>, x<24>, x<25>, x<26>, x<27>, x<28>, x<29>, x<30>, x<31>, x<32>, x<33>, x<34>, x<35>, x<36>, x<37>, x<38>, x<39>, x<40>, x<41>, x<42>, x<43>, x<44>, x<45>, x<46>, x<47>, x<48>, x<49>>"}},{"pid":712215,"tid":712215,"ph":"X","ts":1145,"dur":151548,"name":"Frontend"},{"pid":712215,"tid":712215,"ph":"X","ts":152975,"dur":1137,"name":"Backend"},{"pid":712215,"tid":712215,"ph":"X","ts":5,"dur":154240,"name":"ExecuteCompiler"},{"pid":712215,"tid":712216,"ph":"X","ts":0,"dur":154240,"name":"Total ExecuteCompiler","args":{"count":1,"avg ms":154}},{"pid":712215,"tid":712217,"ph":"X","ts":0,"dur":151618,"name":"Total Frontend","args":{"count":2,"avg ms":75}},{"pid":712215,"tid":712218,"ph":"X","ts":0,"dur":117398,"name":"Total InstantiateFunction","args":{"count":100,"avg ms":1}},{"pid":712215,"tid":712219,"ph":"X","ts":0,"dur":16976,"name":"Total EvaluateAsConstantExpr","args":{"count":9377,"avg ms":0}},{"pid":712215,"tid":712220,"ph":"X","ts":0,"dur":6896,"name":"Total InstantiateClass","args":{"count":250,"avg ms":0}},{"pid":712215,"tid":712221,"ph":"X","ts":0,"dur":3077,"name":"Total Source","args":{"count":1,"avg ms":3}},{"pid":712215,"tid":712222,"ph":"X","ts":0,"dur":1266,"name":"Total ParseClass","args":{"count":7,"avg ms":0}},{"pid":712215,"tid":712223,"ph":"X","ts":0,"dur":1136,"name":"Total Backend","args":{"count":1,"avg ms":1}},{"pid":712215,"tid":712224,"ph":"X","ts":0,"dur":636,"name":"Total ParseFunctionDefinition","args":{"count":6,"avg ms":0}},{"pid":712215,"tid":712225,"ph":"X","ts":0,"dur":387,"name":"Total EvaluateForOverflow","args":{"count":153,"avg ms":0}},{"pid":712215,"tid":712226,"ph":"X","ts":0,"dur":210,"name":"Total CodeGenPasses","args":{"count":1,"avg ms":0}},{"pid":712215,"tid":712227,"ph":"X","ts":0,"dur":195,"name":"Total OptModule","args":{"count":1,"avg ms":0}},{"pid":712215,"tid":712228,"ph":"X","ts":0,"dur":142,"name":"Total EvaluateAsInt","args":{"count":100,"avg ms":0}},{"pid":712215,"tid":712229,"ph":"X","ts":0,"dur":141,"name":"Total EvaluateAsBooleanCondition","args":{"count":100,"avg ms":0}},{"pid":712215,"tid":712230,"ph":"X","ts":0,"dur":130,"name":"Total EvaluateAsInitializer","args":{"count":101,"avg ms":0}},{"pid":712215,"tid":712231,"ph":"X","ts":0,"dur":124,"name":"Total EvaluateAsRValue","args":{"count":201,"avg ms":0}},{"pid":712215,"tid":712232,"ph":"X","ts":0,"dur":36,"name":"Total Optimizer","args":{"count":1,"avg ms":0}},{"pid":712215,"tid":712233,"ph":"X","ts":0,"dur":25,"name":"Total ParseDeclarationOrFunctionDefinition","args":{"count":1,"avg ms":0}},{"pid":712215,"tid":712234,"ph":"X","ts":0,"dur":11,"name":"Total AlwaysInlinerPass","args":{"count":1,"avg ms":0}},{"pid":712215,"tid":712235,"ph":"X","ts":0,"dur":9,"name":"Total CoroConditionalWrapper","args":{"count":1,"avg ms":0}},{"pid":712215,"tid":712236,"ph":"X","ts":0,"dur":1,"name":"Total ProfileSummaryAnalysis","args":{"count":1,"avg ms":0}},{"pid":712215,"tid":712237,"ph":"X","ts":0,"dur":1,"name":"Total InnerAnalysisManagerProxy<AnalysisManager<Function>, Module>","args":{"count":1,"avg ms":0}},{"pid":712215,"tid":712238,"ph":"X","ts":0,"dur":0,"name":"Total ModuleToFunctionPassAdaptor","args":{"count":1,"avg ms":0}},{"pid":712215,"tid":712239,"ph":"X","ts":0,"dur":0,"name":"Total PerformPendingInstantiations","args":{"count":1,"avg ms":0}},{"cat":"","pid":712215,"tid":712215,"ts":0,"ph":"M","name":"process_name","args":{"name":"clang++-19"}},{"cat":"","pid":712215,"tid":712215,"ts":0,"ph":"M","name":"thread_name","args":{"name":"clang++-19"}}],"beginningOfTime":1713595296757802}