{"traceEvents":[{"pid":715961,"tid":715961,"ph":"X","ts":1853,"dur":671,"name":"Source","args":{"detail":"/usr/include/features.h"}},{"pid":715961,"tid":715961,"ph":"X","ts":1613,"dur":1298,"name":"Source","args":{"detail":"/home/kris/Projects/clang-p2996/build/bin/../include/c++/v1/__config"}},{"pid":715961,"tid":715961,"ph":"X","ts":3705,"dur":524,"name":"Source","args":{"detail":"/home/kris/Projects/clang-p2996/build/bin/../include/c++/v1/__type_traits/integral_constant.h"}},{"pid":715961,"tid":715961,"ph":"X","ts":3691,"dur":891,"name":"Source","args":{"detail":"/home/kris/Projects/clang-p2996/build/bin/../include/c++/v1/__type_traits/is_referenceable.h"}},{"pid":715961,"tid":715961,"ph":"X","ts":3675,"dur":1012,"name":"Source","args":{"detail":"/home/kris/Projects/clang-p2996/build/bin/../include/c++/v1/__type_traits/add_lvalue_reference.h"}},{"pid":715961,"tid":715961,"ph":"X","ts":5186,"dur":3047,"name":"Source","args":{"detail":"/home/kris/Projects/clang-p2996/build/bin/../include/c++/v1/cstddef"}},{"pid":715961,"tid":715961,"ph":"X","ts":5165,"dur":3284,"name":"Source","args":{"detail":"/home/kris/Projects/clang-p2996/build/bin/../include/c++/v1/__type_traits/remove_reference.h"}},{"pid":715961,"tid":715961,"ph":"X","ts":4716,"dur":3835,"name":"Source","args":{"detail":"/home/kris/Projects/clang-p2996/build/bin/../include/c++/v1/__type_traits/add_pointer.h"}},{"pid":715961,"tid":715961,"ph":"X","ts":8834,"dur":2144,"name":"Source","args":{"detail":"/home/kris/Projects/clang-p2996/build/bin/../include/c++/v1/__type_traits/aligned_storage.h"}},{"pid":715961,"tid":715961,"ph":"X","ts":11552,"dur":569,"name":"Source","args":{"detail":"/home/kris/Projects/clang-p2996/build/bin/../include/c++/v1/__type_traits/apply_cv.h"}},{"pid":715961,"tid":715961,"ph":"X","ts":12166,"dur":611,"name":"Source","args":{"detail":"/home/kris/Projects/clang-p2996/build/bin/../include/c++/v1/__fwd/pair.h"}},{"pid":715961,"tid":715961,"ph":"X","ts":12146,"dur":1144,"name":"Source","args":{"detail":"/home/kris/Projects/clang-p2996/build/bin/../include/c++/v1/__type_traits/can_extract_key.h"}},{"pid":715961,"tid":715961,"ph":"X","ts":13367,"dur":893,"name":"Source","args":{"detail":"/home/kris/Projects/clang-p2996/build/bin/../include/c++/v1/__type_traits/decay.h"}},{"pid":715961,"tid":715961,"ph":"X","ts":13348,"dur":1888,"name":"Source","args":{"detail":"/home/kris/Projects/clang-p2996/build/bin/../include/c++/v1/__type_traits/common_type.h"}},{"pid":715961,"tid":715961,"ph":"X","ts":13328,"dur":3491,"name":"Source","args":{"detail":"/home/kris/Projects/clang-p2996/build/bin/../include/c++/v1/__type_traits/common_reference.h"}},{"pid":715961,"tid":715961,"ph":"X","ts":18199,"dur":3636,"name":"Source","args":{"detail":"/home/kris/Projects/clang-p2996/build/bin/../include/c++/v1/__type_traits/invoke.h"}},{"pid":715961,"tid":715961,"ph":"X","ts":28420,"dur":922,"name":"Source","args":{"detail":"/home/kris/Projects/clang-p2996/build/bin/../include/c++/v1/__type_traits/is_swappable.h"}},{"pid":715961,"tid":715961,"ph":"X","ts":30054,"dur":687,"name":"Source","args":{"detail":"/usr/include/stdint.h"}},{"pid":715961,"tid":715961,"ph":"X","ts":30020,"dur":826,"name":"Source","args":{"detail":"/home/kris/Projects/clang-p2996/build/lib/clang/19/include/stdint.h"}},{"pid":715961,"tid":715961,"ph":"X","ts":29977,"dur":870,"name":"Source","args":{"detail":"/home/kris/Projects/clang-p2996/build/bin/../include/c++/v1/stdint.h"}},{"pid":715961,"tid":715961,"ph":"X","ts":29957,"dur":1097,"name":"Source","args":{"detail":"/home/kris/Projects/clang-p2996/build/bin/../include/c++/v1/cstdint"}},{"pid":715961,"tid":715961,"ph":"X","ts":29935,"dur":1287,"name":"Source","args":{"detail":"/home/kris/Projects/clang-p2996/build/bin/../include/c++/v1/__type_traits/is_trivially_copyable.h"}},{"pid":715961,"tid":715961,"ph":"X","ts":1581,"dur":32551,"name":"Source","args":{"detail":"/home/kris/Projects/clang-p2996/build/bin/../include/c++/v1/type_traits"}},{"pid":715961,"tid":715961,"ph":"X","ts":1546,"dur":32730,"name":"Source","args":{"detail":"/usr/include/boost/mp11/integral.hpp"}},{"pid":715961,"tid":715961,"ph":"X","ts":34474,"dur":1702,"name":"Source","args":{"detail":"/usr/include/boost/mp11/utility.hpp"}},{"pid":715961,"tid":715961,"ph":"X","ts":34454,"dur":3145,"name":"Source","args":{"detail":"/usr/include/boost/mp11/detail/mp_append.hpp"}},{"pid":715961,"tid":715961,"ph":"X","ts":1532,"dur":37079,"name":"Source","args":{"detail":"/usr/include/boost/mp11/list.hpp"}},{"pid":715961,"tid":715961,"ph":"X","ts":38715,"dur":1572,"name":"Source","args":{"detail":"/usr/include/boost/mp11/function.hpp"}},{"pid":715961,"tid":715961,"ph":"X","ts":38696,"dur":3004,"name":"Source","args":{"detail":"/usr/include/boost/mp11/set.hpp"}},{"pid":715961,"tid":715961,"ph":"X","ts":42016,"dur":601,"name":"Source","args":{"detail":"/home/kris/Projects/clang-p2996/build/bin/../include/c++/v1/__utility/as_const.h"}},{"pid":715961,"tid":715961,"ph":"X","ts":43627,"dur":545,"name":"ParseClass","args":{"detail":"std::__libcpp_numeric_limits"}},{"pid":715961,"tid":715961,"ph":"X","ts":44280,"dur":628,"name":"ParseClass","args":{"detail":"std::__libcpp_numeric_limits"}},{"pid":715961,"tid":715961,"ph":"X","ts":44925,"dur":579,"name":"ParseClass","args":{"detail":"std::__libcpp_numeric_limits"}},{"pid":715961,"tid":715961,"ph":"X","ts":45521,"dur":703,"name":"ParseClass","args":{"detail":"std::__libcpp_numeric_limits"}},{"pid":715961,"tid":715961,"ph":"X","ts":46248,"dur":645,"name":"ParseClass","args":{"detail":"std::__libcpp_numeric_limits"}},{"pid":715961,"tid":715961,"ph":"X","ts":46912,"dur":754,"name":"ParseClass","args":{"detail":"std::__libcpp_numeric_limits"}},{"pid":715961,"tid":715961,"ph":"X","ts":47684,"dur":542,"name":"ParseClass","args":{"detail":"std::numeric_limits"}},{"pid":715961,"tid":715961,"ph":"X","ts":43440,"dur":5167,"name":"Source","args":{"detail":"/home/kris/Projects/clang-p2996/build/bin/../include/c++/v1/limits"}},{"pid":715961,"tid":715961,"ph":"X","ts":42901,"dur":6760,"name":"Source","args":{"detail":"/home/kris/Projects/clang-p2996/build/bin/../include/c++/v1/__utility/cmp.h"}},{"pid":715961,"tid":715961,"ph":"X","ts":49711,"dur":1517,"name":"Source","args":{"detail":"/home/kris/Projects/clang-p2996/build/bin/../include/c++/v1/__utility/exception_guard.h"}},{"pid":715961,"tid":715961,"ph":"X","ts":52195,"dur":529,"name":"Source","args":{"detail":"/home/kris/Projects/clang-p2996/build/bin/../include/c++/v1/__utility/integer_sequence.h"}},{"pid":715961,"tid":715961,"ph":"X","ts":53229,"dur":1775,"name":"ParseClass","args":{"detail":"std::partial_ordering"}},{"pid":715961,"tid":715961,"ph":"X","ts":53223,"dur":1788,"name":"ParseDeclarationOrFunctionDefinition","args":{"detail":"/home/kris/Projects/clang-p2996/build/bin/../include/c++/v1/__compare/ordering.h:43:1"}},{"pid":715961,"tid":715961,"ph":"X","ts":55187,"dur":1645,"name":"ParseClass","args":{"detail":"std::weak_ordering"}},{"pid":715961,"tid":715961,"ph":"X","ts":55179,"dur":1660,"name":"ParseDeclarationOrFunctionDefinition","args":{"detail":"/home/kris/Projects/clang-p2996/build/bin/../include/c++/v1/__compare/ordering.h:119:1"}},{"pid":715961,"tid":715961,"ph":"X","ts":56981,"dur":1842,"name":"ParseClass","args":{"detail":"std::strong_ordering"}},{"pid":715961,"tid":715961,"ph":"X","ts":56974,"dur":1856,"name":"ParseDeclarationOrFunctionDefinition","args":{"detail":"/home/kris/Projects/clang-p2996/build/bin/../include/c++/v1/__compare/ordering.h:189:1"}},{"pid":715961,"tid":715961,"ph":"X","ts":52844,"dur":6201,"name":"Source","args":{"detail":"/home/kris/Projects/clang-p2996/build/bin/../include/c++/v1/__compare/ordering.h"}},{"pid":715961,"tid":715961,"ph":"X","ts":52806,"dur":7414,"name":"Source","args":{"detail":"/home/kris/Projects/clang-p2996/build/bin/../include/c++/v1/__compare/common_comparison_category.h"}},{"pid":715961,"tid":715961,"ph":"X","ts":60289,"dur":1251,"name":"Source","args":{"detail":"/home/kris/Projects/clang-p2996/build/bin/../include/c++/v1/__compare/three_way_comparable.h"}},{"pid":715961,"tid":715961,"ph":"X","ts":60265,"dur":1514,"name":"Source","args":{"detail":"/home/kris/Projects/clang-p2996/build/bin/../include/c++/v1/__compare/synth_three_way.h"}},{"pid":715961,"tid":715961,"ph":"X","ts":62837,"dur":1479,"name":"Source","args":{"detail":"/home/kris/Projects/clang-p2996/build/bin/../include/c++/v1/__concepts/swappable.h"}},{"pid":715961,"tid":715961,"ph":"X","ts":62818,"dur":1626,"name":"Source","args":{"detail":"/home/kris/Projects/clang-p2996/build/bin/../include/c++/v1/__concepts/movable.h"}},{"pid":715961,"tid":715961,"ph":"X","ts":62342,"dur":2191,"name":"Source","args":{"detail":"/home/kris/Projects/clang-p2996/build/bin/../include/c++/v1/__concepts/copyable.h"}},{"pid":715961,"tid":715961,"ph":"X","ts":65267,"dur":634,"name":"Source","args":{"detail":"/home/kris/Projects/clang-p2996/build/bin/../include/c++/v1/__iterator/incrementable_traits.h"}},{"pid":715961,"tid":715961,"ph":"X","ts":65977,"dur":2522,"name":"Source","args":{"detail":"/home/kris/Projects/clang-p2996/build/bin/../include/c++/v1/__iterator/iterator_traits.h"}},{"pid":715961,"tid":715961,"ph":"X","ts":65937,"dur":3288,"name":"Source","args":{"detail":"/home/kris/Projects/clang-p2996/build/bin/../include/c++/v1/__iterator/iter_move.h"}},{"pid":715961,"tid":715961,"ph":"X","ts":69289,"dur":2143,"name":"Source","args":{"detail":"/home/kris/Projects/clang-p2996/build/bin/../include/c++/v1/__memory/pointer_traits.h"}},{"pid":715961,"tid":715961,"ph":"X","ts":64588,"dur":9621,"name":"Source","args":{"detail":"/home/kris/Projects/clang-p2996/build/bin/../include/c++/v1/__iterator/concepts.h"}},{"pid":715961,"tid":715961,"ph":"X","ts":62324,"dur":12316,"name":"Source","args":{"detail":"/home/kris/Projects/clang-p2996/build/bin/../include/c++/v1/__fwd/subrange.h"}},{"pid":715961,"tid":715961,"ph":"X","ts":74713,"dur":562,"name":"Source","args":{"detail":"/home/kris/Projects/clang-p2996/build/bin/../include/c++/v1/__tuple/tuple_like.h"}},{"pid":715961,"tid":715961,"ph":"X","ts":74692,"dur":1146,"name":"Source","args":{"detail":"/home/kris/Projects/clang-p2996/build/bin/../include/c++/v1/__tuple/pair_like.h"}},{"pid":715961,"tid":715961,"ph":"X","ts":75911,"dur":602,"name":"Source","args":{"detail":"/home/kris/Projects/clang-p2996/build/bin/../include/c++/v1/__tuple/tuple_element.h"}},{"pid":715961,"tid":715961,"ph":"X","ts":75893,"dur":1116,"name":"Source","args":{"detail":"/home/kris/Projects/clang-p2996/build/bin/../include/c++/v1/__tuple/make_tuple_types.h"}},{"pid":715961,"tid":715961,"ph":"X","ts":75871,"dur":2480,"name":"Source","args":{"detail":"/home/kris/Projects/clang-p2996/build/bin/../include/c++/v1/__tuple/sfinae_helpers.h"}},{"pid":715961,"tid":715961,"ph":"X","ts":79016,"dur":2801,"name":"ParseClass","args":{"detail":"std::pair"}},{"pid":715961,"tid":715961,"ph":"X","ts":52776,"dur":31558,"name":"Source","args":{"detail":"/home/kris/Projects/clang-p2996/build/bin/../include/c++/v1/__utility/pair.h"}},{"pid":715961,"tid":715961,"ph":"X","ts":85998,"dur":647,"name":"Source","args":{"detail":"/home/kris/Projects/clang-p2996/build/bin/../include/c++/v1/__type_traits/promote.h"}},{"pid":715961,"tid":715961,"ph":"X","ts":85974,"dur":2509,"name":"Source","args":{"detail":"/home/kris/Projects/clang-p2996/build/bin/../include/c++/v1/__math/exponential_functions.h"}},{"pid":715961,"tid":715961,"ph":"X","ts":88531,"dur":1640,"name":"Source","args":{"detail":"/home/kris/Projects/clang-p2996/build/bin/../include/c++/v1/__math/traits.h"}},{"pid":715961,"tid":715961,"ph":"X","ts":90363,"dur":2687,"name":"ParseClass","args":{"detail":"std::__strong_order::__fn"}},{"pid":715961,"tid":715961,"ph":"X","ts":90354,"dur":2700,"name":"ParseDeclarationOrFunctionDefinition","args":{"detail":"/home/kris/Projects/clang-p2996/build/bin/../include/c++/v1/__compare/strong_order.h:42:1"}},{"pid":715961,"tid":715961,"ph":"X","ts":85752,"dur":7395,"name":"Source","args":{"detail":"/home/kris/Projects/clang-p2996/build/bin/../include/c++/v1/__compare/strong_order.h"}},{"pid":715961,"tid":715961,"ph":"X","ts":93310,"dur":1395,"name":"ParseClass","args":{"detail":"std::__weak_order::__fn"}},{"pid":715961,"tid":715961,"ph":"X","ts":93303,"dur":1406,"name":"ParseDeclarationOrFunctionDefinition","args":{"detail":"/home/kris/Projects/clang-p2996/build/bin/../include/c++/v1/__compare/weak_order.h:35:1"}},{"pid":715961,"tid":715961,"ph":"X","ts":85730,"dur":9058,"name":"Source","args":{"detail":"/home/kris/Projects/clang-p2996/build/bin/../include/c++/v1/__compare/weak_order.h"}},{"pid":715961,"tid":715961,"ph":"X","ts":94945,"dur":662,"name":"ParseClass","args":{"detail":"std::__partial_order::__fn"}},{"pid":715961,"tid":715961,"ph":"X","ts":94938,"dur":673,"name":"ParseDeclarationOrFunctionDefinition","args":{"detail":"/home/kris/Projects/clang-p2996/build/bin/../include/c++/v1/__compare/partial_order.h:33:1"}},{"pid":715961,"tid":715961,"ph":"X","ts":85414,"dur":10270,"name":"Source","args":{"detail":"/home/kris/Projects/clang-p2996/build/bin/../include/c++/v1/__compare/partial_order.h"}},{"pid":715961,"tid":715961,"ph":"X","ts":95799,"dur":609,"name":"ParseClass","args":{"detail":"std::__compare_partial_order_fallback::__fn"}},{"pid":715961,"tid":715961,"ph":"X","ts":95792,"dur":619,"name":"ParseDeclarationOrFunctionDefinition","args":{"detail":"/home/kris/Projects/clang-p2996/build/bin/../include/c++/v1/__compare/compare_partial_order_fallback.h:30:1"}},{"pid":715961,"tid":715961,"ph":"X","ts":85398,"dur":11085,"name":"Source","args":{"detail":"/home/kris/Projects/clang-p2996/build/bin/../include/c++/v1/__compare/compare_partial_order_fallback.h"}},{"pid":715961,"tid":715961,"ph":"X","ts":96655,"dur":605,"name":"ParseClass","args":{"detail":"std::__compare_strong_order_fallback::__fn"}},{"pid":715961,"tid":715961,"ph":"X","ts":96648,"dur":616,"name":"ParseDeclarationOrFunctionDefinition","args":{"detail":"/home/kris/Projects/clang-p2996/build/bin/../include/c++/v1/__compare/compare_strong_order_fallback.h:30:1"}},{"pid":715961,"tid":715961,"ph":"X","ts":96528,"dur":807,"name":"Source","args":{"detail":"/home/kris/Projects/clang-p2996/build/bin/../include/c++/v1/__compare/compare_strong_order_fallback.h"}},{"pid":715961,"tid":715961,"ph":"X","ts":97877,"dur":572,"name":"ParseClass","args":{"detail":"std::__compare_weak_order_fallback::__fn"}},{"pid":715961,"tid":715961,"ph":"X","ts":97871,"dur":582,"name":"ParseDeclarationOrFunctionDefinition","args":{"detail":"/home/kris/Projects/clang-p2996/build/bin/../include/c++/v1/__compare/compare_weak_order_fallback.h:30:1"}},{"pid":715961,"tid":715961,"ph":"X","ts":97778,"dur":750,"name":"Source","args":{"detail":"/home/kris/Projects/clang-p2996/build/bin/../include/c++/v1/__compare/compare_weak_order_fallback.h"}},{"pid":715961,"tid":715961,"ph":"X","ts":98571,"dur":1729,"name":"Source","args":{"detail":"/home/kris/Projects/clang-p2996/build/bin/../include/c++/v1/__compare/is_eq.h"}},{"pid":715961,"tid":715961,"ph":"X","ts":85375,"dur":14965,"name":"Source","args":{"detail":"/home/kris/Projects/clang-p2996/build/bin/../include/c++/v1/compare"}},{"pid":715961,"tid":715961,"ph":"X","ts":100380,"dur":508,"name":"Source","args":{"detail":"/home/kris/Projects/clang-p2996/build/bin/../include/c++/v1/initializer_list"}},{"pid":715961,"tid":715961,"ph":"X","ts":41995,"dur":58926,"name":"Source","args":{"detail":"/home/kris/Projects/clang-p2996/build/bin/../include/c++/v1/utility"}},{"pid":715961,"tid":715961,"ph":"X","ts":41962,"dur":64053,"name":"Source","args":{"detail":"/usr/include/boost/mp11/detail/mp_with_index.hpp"}},{"pid":715961,"tid":715961,"ph":"X","ts":38665,"dur":74888,"name":"Source","args":{"detail":"/usr/include/boost/mp11/algorithm.hpp"}},{"pid":715961,"tid":715961,"ph":"X","ts":113606,"dur":814,"name":"Source","args":{"detail":"/usr/include/boost/mp11/map.hpp"}},{"pid":715961,"tid":715961,"ph":"X","ts":114459,"dur":587,"name":"Source","args":{"detail":"/usr/include/boost/mp11/bind.hpp"}},{"pid":715961,"tid":715961,"ph":"X","ts":115159,"dur":1113,"name":"Source","args":{"detail":"/home/kris/Projects/clang-p2996/build/bin/../include/c++/v1/__memory/allocator_arg_t.h"}},{"pid":715961,"tid":715961,"ph":"X","ts":116316,"dur":598,"name":"Source","args":{"detail":"/home/kris/Projects/clang-p2996/build/bin/../include/c++/v1/__tuple/find_index.h"}},{"pid":715961,"tid":715961,"ph":"X","ts":117410,"dur":933,"name":"ParseClass","args":{"detail":"std::__tuple_leaf"}},{"pid":715961,"tid":715961,"ph":"X","ts":118388,"dur":708,"name":"ParseClass","args":{"detail":"std::__tuple_leaf"}},{"pid":715961,"tid":715961,"ph":"X","ts":119252,"dur":987,"name":"ParseClass","args":{"detail":"std::__tuple_impl"}},{"pid":715961,"tid":715961,"ph":"X","ts":120449,"dur":6232,"name":"ParseClass","args":{"detail":"std::tuple"}},{"pid":715961,"tid":715961,"ph":"X","ts":115126,"dur":17117,"name":"Source","args":{"detail":"/home/kris/Projects/clang-p2996/build/bin/../include/c++/v1/tuple"}},{"pid":715961,"tid":715961,"ph":"X","ts":115086,"dur":18180,"name":"Source","args":{"detail":"/usr/include/boost/mp11/tuple.hpp"}},{"pid":715961,"tid":715961,"ph":"X","ts":1494,"dur":131774,"name":"Source","args":{"detail":"/usr/include/boost/mp11.hpp"}},{"pid":715961,"tid":715961,"ph":"X","ts":1129,"dur":134506,"name":"Frontend"},{"pid":715961,"tid":715961,"ph":"X","ts":136068,"dur":1148,"name":"Backend"},{"pid":715961,"tid":715961,"ph":"X","ts":9,"dur":137342,"name":"ExecuteCompiler"},{"pid":715961,"tid":715962,"ph":"X","ts":0,"dur":137342,"name":"Total ExecuteCompiler","args":{"count":1,"avg ms":137}},{"pid":715961,"tid":715963,"ph":"X","ts":0,"dur":134572,"name":"Total Frontend","args":{"count":2,"avg ms":67}},{"pid":715961,"tid":715964,"ph":"X","ts":0,"dur":131773,"name":"Total Source","args":{"count":1,"avg ms":131}},{"pid":715961,"tid":715965,"ph":"X","ts":0,"dur":52832,"name":"Total ParseClass","args":{"count":726,"avg ms":0}},{"pid":715961,"tid":715966,"ph":"X","ts":0,"dur":20405,"name":"Total ParseDeclarationOrFunctionDefinition","args":{"count":120,"avg ms":0}},{"pid":715961,"tid":715967,"ph":"X","ts":0,"dur":10386,"name":"Total ParseFunctionDefinition","args":{"count":200,"avg ms":0}},{"pid":715961,"tid":715968,"ph":"X","ts":0,"dur":1680,"name":"Total InstantiateClass","args":{"count":23,"avg ms":0}},{"pid":715961,"tid":715969,"ph":"X","ts":0,"dur":1147,"name":"Total Backend","args":{"count":1,"avg ms":1}},{"pid":715961,"tid":715970,"ph":"X","ts":0,"dur":403,"name":"Total InstantiateFunction","args":{"count":2,"avg ms":0}},{"pid":715961,"tid":715971,"ph":"X","ts":0,"dur":294,"name":"Total EvaluateAsConstantExpr","args":{"count":501,"avg ms":0}},{"pid":715961,"tid":715972,"ph":"X","ts":0,"dur":257,"name":"Total isPotentialConstantExpr","args":{"count":106,"avg ms":0}},{"pid":715961,"tid":715973,"ph":"X","ts":0,"dur":245,"name":"Total EvaluateAsRValue","args":{"count":587,"avg ms":0}},{"pid":715961,"tid":715974,"ph":"X","ts":0,"dur":243,"name":"Total EvaluateAsInitializer","args":{"count":202,"avg ms":0}},{"pid":715961,"tid":715975,"ph":"X","ts":0,"dur":202,"name":"Total CodeGenPasses","args":{"count":1,"avg ms":0}},{"pid":715961,"tid":715976,"ph":"X","ts":0,"dur":186,"name":"Total OptModule","args":{"count":1,"avg ms":0}},{"pid":715961,"tid":715977,"ph":"X","ts":0,"dur":184,"name":"Total EvaluateAsBooleanCondition","args":{"count":114,"avg ms":0}},{"pid":715961,"tid":715978,"ph":"X","ts":0,"dur":118,"name":"Total EvaluateForOverflow","args":{"count":52,"avg ms":0}},{"pid":715961,"tid":715979,"ph":"X","ts":0,"dur":31,"name":"Total Optimizer","args":{"count":1,"avg ms":0}},{"pid":715961,"tid":715980,"ph":"X","ts":0,"dur":20,"name":"Total EvaluateAsInt","args":{"count":33,"avg ms":0}},{"pid":715961,"tid":715981,"ph":"X","ts":0,"dur":15,"name":"Total AlwaysInlinerPass","args":{"count":1,"avg ms":0}},{"pid":715961,"tid":715982,"ph":"X","ts":0,"dur":14,"name":"Total EvaluateKnownConstInt","args":{"count":141,"avg ms":0}},{"pid":715961,"tid":715983,"ph":"X","ts":0,"dur":13,"name":"Total isIntegerConstantExpr","args":{"count":17,"avg ms":0}},{"pid":715961,"tid":715984,"ph":"X","ts":0,"dur":4,"name":"Total InnerAnalysisManagerProxy<AnalysisManager<Function>, Module>","args":{"count":1,"avg ms":0}},{"pid":715961,"tid":715985,"ph":"X","ts":0,"dur":2,"name":"Total CoroConditionalWrapper","args":{"count":1,"avg ms":0}},{"pid":715961,"tid":715986,"ph":"X","ts":0,"dur":1,"name":"Total ProfileSummaryAnalysis","args":{"count":1,"avg ms":0}},{"pid":715961,"tid":715987,"ph":"X","ts":0,"dur":1,"name":"Total ModuleToFunctionPassAdaptor","args":{"count":1,"avg ms":0}},{"pid":715961,"tid":715988,"ph":"X","ts":0,"dur":0,"name":"Total PerformPendingInstantiations","args":{"count":1,"avg ms":0}},{"cat":"","pid":715961,"tid":715961,"ts":0,"ph":"M","name":"process_name","args":{"name":"clang++-19"}},{"cat":"","pid":715961,"tid":715961,"ts":0,"ph":"M","name":"thread_name","args":{"name":"clang++-19"}}],"beginningOfTime":1713595802927270}