{"traceEvents":[{"pid":719916,"tid":719916,"ph":"X","ts":1030,"dur":7484,"name":"Frontend"},{"pid":719916,"tid":719916,"ph":"X","ts":8585,"dur":772,"name":"Backend"},{"pid":719916,"tid":719916,"ph":"X","ts":17,"dur":9455,"name":"ExecuteCompiler"},{"pid":719916,"tid":719917,"ph":"X","ts":0,"dur":9455,"name":"Total ExecuteCompiler","args":{"count":1,"avg ms":9}},{"pid":719916,"tid":719918,"ph":"X","ts":0,"dur":7538,"name":"Total Frontend","args":{"count":2,"avg ms":3}},{"pid":719916,"tid":719919,"ph":"X","ts":0,"dur":772,"name":"Total Backend","args":{"count":1,"avg ms":0}},{"pid":719916,"tid":719920,"ph":"X","ts":0,"dur":175,"name":"Total CodeGenPasses","args":{"count":1,"avg ms":0}},{"pid":719916,"tid":719921,"ph":"X","ts":0,"dur":161,"name":"Total OptModule","args":{"count":1,"avg ms":0}},{"pid":719916,"tid":719922,"ph":"X","ts":0,"dur":37,"name":"Total EvaluateAsRValue","args":{"count":40,"avg ms":0}},{"pid":719916,"tid":719923,"ph":"X","ts":0,"dur":34,"name":"Total EvaluateAsConstantExpr","args":{"count":40,"avg ms":0}},{"pid":719916,"tid":719924,"ph":"X","ts":0,"dur":26,"name":"Total ParseClass","args":{"count":1,"avg ms":0}},{"pid":719916,"tid":719925,"ph":"X","ts":0,"dur":18,"name":"Total Optimizer","args":{"count":1,"avg ms":0}},{"pid":719916,"tid":719926,"ph":"X","ts":0,"dur":5,"name":"Total AlwaysInlinerPass","args":{"count":1,"avg ms":0}},{"pid":719916,"tid":719927,"ph":"X","ts":0,"dur":3,"name":"Total PerformPendingInstantiations","args":{"count":1,"avg ms":0}},{"pid":719916,"tid":719928,"ph":"X","ts":0,"dur":1,"name":"Total ProfileSummaryAnalysis","args":{"count":1,"avg ms":0}},{"pid":719916,"tid":719929,"ph":"X","ts":0,"dur":1,"name":"Total CoroConditionalWrapper","args":{"count":1,"avg ms":0}},{"pid":719916,"tid":719930,"ph":"X","ts":0,"dur":0,"name":"Total ModuleToFunctionPassAdaptor","args":{"count":1,"avg ms":0}},{"pid":719916,"tid":719931,"ph":"X","ts":0,"dur":0,"name":"Total InnerAnalysisManagerProxy<FunctionAnalysisManager, Module>","args":{"count":1,"avg ms":0}},{"cat":"","pid":719916,"tid":719916,"ts":0,"ph":"M","name":"process_name","args":{"name":"clang"}},{"cat":"","pid":719916,"tid":719916,"ts":0,"ph":"M","name":"thread_name","args":{"name":"clang++-17"}}],"beginningOfTime":1713596413042170}